[
  {
    "page": 1,
    "summary": "このページは日立の家庭用冷凍冷蔵庫R-HWS47X型の取扱説明書の表紙で、製品の型式や開き方の説明、取扱説明書の大切さが記載されています。また、日立家電メンバーズクラブへの製品登録を促し、安全上の注意の参照先や初回使用時の冷却時間について案内しています。",
    "content": "```markdown\n![R-HWS47X型](R-HWS47X型)\n\n# HITACHI  \n## Inspire the Next\n\n# 取扱説明書  \n### 保証書付き  \n保証書は裏表紙に付いています\n\n---\n\n## 日立冷凍冷蔵庫 家庭用\n\n### 型式  \nアール　エイチダブリューエス　エックス  \n**R-HWS47X**  \n（右開き）\n\nアール　エイチダブリューエス　エックス エル  \n**R-HWS47XL**  \n（左開き）\n\n---\n\nこのたびは日立冷凍冷蔵庫をお買い上げいただき、まことにありがとうございました。  \nこの冷凍冷蔵庫は家庭用です。業務用や食品収納以外の目的にはご使用にならないでください。  \n**この取扱説明書をよくお読みになり、正しくご使用ください。**  \nお読みになったあとは、大切に保管してください。\n\n---\n\n### 日立家電メンバーズクラブのMy家電への製品登録をおすすめします\n\nさまざまなサービスをご利用いただけます。  \n- 家電品の登録・管理  \n- お役立ち情報  \n- 安全点検サービス料金割引  \n- パーツショップ送料特典  \n- お知らせ  \n\n登録はこちら（QRコード）\n\n詳しくは →（P.2）\n\n---\n\n「安全上のご注意」をお読みいただき正しくお使いください。→（P.4〜5）\n\n---\n\n### はじめてお使いになるときは、冷えるまで時間がかかります  \n庫内が冷えるまでに24時間以上かかることがあります。  \n→（P.7）\n\n説明動画（QRコード）\n\n---\n\n日本国内家庭用  \nUse only in Japan\n```",
    "metadata": {
      "topics": [
        "日立冷凍冷蔵庫の型式",
        "製品登録の案内",
        "使用上の注意",
        "保証書情報",
        "初回使用時の冷却時間"
      ],
      "keywords": [
        "日立",
        "冷凍冷蔵庫",
        "R-HWS47X",
        "R-HWS47XL",
        "取扱説明書",
        "家庭用",
        "保証書",
        "安全上のご注意",
        "家電メンバーズクラブ",
        "冷却時間"
      ],
      "section_header": "表紙",
      "page_type": "cover"
    }
  },
  {
    "page": 2,
    "summary": "日立家電メンバーズクラブに無料登録すると、製品管理や会員限定の特典が利用可能です。特典には安全点検サービスの料金割引やパーツショップの送料特典があり、省エネのための冷蔵庫の使い方も紹介されています。また、よくあるお問い合わせも掲載されています。",
    "content": "```markdown\n# 日立家電メンバーズクラブのご案内\n\n日立家電メンバーズクラブのMy家電に製品をご登録（無料）いただくとスマートフォンやパソコンでお持ちの家電品を一覧管理でき、サポート情報や会員限定の特典などをご利用いただけます。\n\n## ■My家電への製品登録\n1. コードを読み取る  \n![QRコード 登録はこちら]\n\n2. 画面の案内に従って家電品を登録 ※1  \n※1 家電品の登録には型式と色調が必要です。  \n冷蔵室ドア内側の銘版（シール）をご確認ください。  \nまた、銘版（シール）に記載されているコードから登録することで、型式と色調の入力を省略できます。\n\n---\n\n- コードが読み取れない場合は、URLを入力して表示される画面の案内に従ってください。  \nhttps://kadenfan.hitachi.co.jp/my/\n- ご利用の環境によっては、コードの読み取り、ページの表示ができない場合があります。\n\n---\n\n## ■日立家電メンバーズクラブ会員限定のアフターサービス特典のご紹介\n- ▶ 安全点検サービス料金割引（webからの申込限定）  \n  ご使用の家電品を長くご利用いただくための安全点検における標準技術料が、Webでご依頼いただくと10%引きになります。  \n  ※サービスには、不具合の改善や修理作業などは含まれておりません。  \n  ※一部対象外製品がございます。\n\n- ▶ パーツショップ送料特典  \n  付属品や別売商品をパーツショップ（日立の家電消耗品・部品直販インターネット販売）で商品価格総額2,000円（税込）以上お買い上げいただくと送料が無料になります。  \n  ※代引きの場合は、代引き手数料が別途かかります。\n\n詳しくは、日立家電メンバーズクラブのホームページをご覧ください。  \n※特典の内容は予告なく変更する場合がございます。  \n●ご利用の際は、通信費などの費用がかかります。  \n●「使いかた動画」のホームページ掲載は、予告なく中止することがあります。\n\n---\n\n## その他サポートのご案内\n- ■ よくあるご質問  \n  ・会員登録前でもご利用いただけます。  \n- ■ お問い合わせ  \n  ・ご利用の際は、通信費などの費用がかかります。\n\n---\n\n# 省エネのための上手な使いかた\n\n1. ドアの開閉は少なく、開けている時間は短く  \n   頻繁にドアを開閉したり、ドアを長い時間開けていると、冷気が逃げて電気のムダになります。\n\n2. 食品の詰め込みすぎは禁物  \n   食品を詰め込みすぎると、冷気の流れが悪くなり庫内が均一に冷えないばかりでなく、余分な電気を消費します。奥の壁が見える程度にすき間をあけてください。\n\n3. 熱いものは冷ましてから  \n   熱いものを入れると、庫内温度が上昇し、周りの食品温度も上げてしまいます。\n\n4. 冷蔵庫の周囲に適度なすき間をあけて  \n   周囲のすき間がない状態で設置すると、放熱ができず電気のムダになります。\n\n5. 傷んだドアパッキンは取り替えて  \n   傷んでいるパッキンのすき間から冷気が漏れて電気のムダになります。はがき等をはさんで落ちるようでしたら、パッキンを取り替えてください。\n\n---\n\n# よくあるお問い合わせ\n\n| 項目                 | ページ番号       |\n|--------------------|----------------|\n| 氷ができないときは       | →(P.29)        |\n| 冷蔵庫が冷えないときは     | →(P.28)        |\n| 霜や露がつくときは        | →(P.28,30)     |\n```\n",
    "metadata": {
      "topics": [
        "日立家電メンバーズクラブ登録方法",
        "会員限定アフターサービス特典",
        "省エネのための冷蔵庫の使い方",
        "よくあるお問い合わせ"
      ],
      "keywords": [
        "日立家電メンバーズクラブ",
        "My家電",
        "QRコード登録",
        "安全点検サービス",
        "パーツショップ送料特典",
        "省エネ",
        "冷蔵庫",
        "ドアパッキン",
        "電気のムダ"
      ],
      "section_header": "サポート・メンテナンス",
      "page_type": "instruction"
    }
  },
  {
    "page": 3,
    "summary": "このページは冷蔵庫の取扱説明書の目次で、安全上の注意事項から始まり、各室の使い方、お手入れ方法、お困りのときの対処法まで詳細に記載されています。また、製品の仕様や保証・アフターサービスについても案内が含まれています。",
    "content": "```markdown\n# もくじ\n\n## ご使用の前に\n- 安全上のご注意 ........................................ 4  \n- 準備する ............................................... 6  \n  - 使いはじめるまでの手順 ............................... 6  \n  - 地震にそなえて ..................................... 7  \n- 確認する ................................................ 8  \n  - 操作パネルのはたらき／各室のなまえ .................. 8  \n  - 保存食品例 ........................................... 9  \n\n## 使いかた\n- 冷蔵室 ............................................... 10  \n  - 各部のなまえ ........................................ 10  \n  - 「まるごとチルド」を使う ........................... 10  \n  - 食品を急いで冷やしたいとき〔クイック冷却を使う〕.. 11  \n  - ポケット・棚の高さをかえる .......................... 11  \n  - 小物ケースを使う ..................................... 12  \n- 特鮮氷温ルーム ....................................... 13  \n  - 収納食品 .............................................. 13  \n  - 特鮮氷温ケースを開閉する ............................ 13  \n- 製氷室（自動製氷機） ................................ 14  \n  - 氷をつくる（製氷） .................................. 14  \n  - 氷の収納量・製氷時間 ................................. 15  \n  - 急いで氷をつくる（急速製氷） ....................... 15  \n  - 氷をつくらない（製氷停止） .......................... 15  \n  - 「製氷」または、冷凍「強め・弱め」と  \n    冷蔵「弱め」のランプが点滅しているとき .......... 15  \n- 冷凍室 ............................................... 16  \n  - 収納食品／食品を収納するとき ....................... 16  \n  - 食品を急いで凍らせる〔急冷凍〕を使う) .............. 17  \n  - 温度の調節（冷凍室） ................................ 17  \n- 野菜室 ............................................... 18  \n  - 収納食品／食品を収納するとき ....................... 18  \n  - 野菜を保存するときのコツ ............................. 19  \n- いろいろな機能 ....................................... 20  \n  - 温度微調節（冷蔵室・冷凍室） ........................ 20  \n  - ドアアラーム .......................................... 21  \n  - ドアアラームと操作音の音量調整 ..................... 21  \n  - トリプルパワー脱臭（冷蔵室） ........................ 21  \n- 節電する ............................................. 22  \n  - 節電モード ............................................ 22  \n\n## お手入れ\n- お手入れ ............................................. 23  \n  - 電源プラグ／ドアパッキング ........................ 23  \n  - ドア表面／各棚・ポケット／汗受け部 ................ 23  \n  - 冷蔵庫背面・側面・床／ケース ....................... 23  \n  - 特鮮氷温ルーム ....................................... 24  \n  - 給水タンク ........................................... 24  \n  - 製氷おそうじ ......................................... 25  \n- 部品の取りはずしかた・取り付けかた .................. 26  \n  - 高さかわるん棚上段・中段 ............................ 26  \n  - 高さかわるん棚下段 ................................... 26  \n  - 固定棚 ................................................ 26  \n  - 棚しきり ............................................. 26  \n  - ドアポケット .......................................... 26  \n  - 特鮮氷温ケース ....................................... 26  \n  - 製氷ケース（製氷室）・上段フリーザーケース（冷凍室上段）  \n    .................................................... 27  \n  - 薄物ケース・小物ケース・大物ケース（冷凍室下段）  \n    .................................................... 27  \n  - 上段ケース・しきり・下段ケース（野菜室） .......... 27  \n  - 引き出しドアの取りはずしかた・取り付けかた ........ 27  \n\n## お困りのときは・アフターサービス\n- お困りのときは ....................................... 28  \n  - 使いはじめ ........................................... 28  \n  - 冷えない ............................................. 28  \n  - 霜や露がつく ......................................... 28  \n  - 自動製氷 ............................................. 29  \n  - 操作パネルのランプが点滅している ................... 30  \n  - 野菜室が気になる ..................................... 30  \n  - 特鮮氷温ルームが気になる ............................ 31  \n  - ドアの段差や傾きが気になる .......................... 31  \n  - においが気になる ..................................... 31  \n  - 冷え過ぎる ............................................ 31  \n  - 冷蔵庫が熱くなる ..................................... 31  \n  - 音が気になる ......................................... 32  \n  - その他 ................................................ 33  \n  - 移動・運搬の準備（引っ越しをする） ................ 33  \n- 仕様 .................................................... 34  \n  - 消費電力量について .................................. 34  \n  - 冷凍室の性能 ......................................... 34  \n- 収納できる食品の重さの目安 ........................... 34  \n- 別売部品 ............................................... 35  \n- お客様ご相談窓口 ..................................... 35  \n- 保証とアフターサービス ............................... 36  \n  - 修理を依頼されるときは（出張修理） ................ 36  \n  - 保証書 ................................................ 36  \n```",
    "metadata": {
      "topics": [
        "安全上のご注意",
        "使いかた",
        "お手入れ",
        "お困りのときは・アフターサービス",
        "仕様・保証"
      ],
      "keywords": [
        "冷蔵庫",
        "製氷室",
        "冷凍室",
        "野菜室",
        "節電モード",
        "トリプルパワー脱臭",
        "クイック冷却",
        "急速製氷",
        "冷蔵室",
        "操作パネル"
      ],
      "section_header": "もくじ",
      "page_type": "toc"
    }
  },
  {
    "page": 4,
    "summary": "このページは冷蔵庫の安全使用に関する注意事項を説明しており、感電や火災、けがを防ぐための設置方法や電源の取り扱い、普段の使用時の注意点を詳述しています。また、万が一の事故時の対応や修理時の注意も記載されています。警告や禁止、指示の各マークに従って正しく使用することが強調されています。",
    "content": "```markdown\n# 安全上のご注意　必ずお守りください\n\nお使いになる人や、ほかの人への危害、財産への損害を未然に防止するため、お守りいただくことを説明しています。また、本文中の注意事項についてもよくお読みのうえ、正しくお使いください。\n\n■ここに示した注記事項は、表示内容を無視して誤った使いかたをしたときに生じる危害や損害の程度を、次の表示で区分し、説明しています。\n\n| 警告マーク | 説明                               | 意味                             |\n|-------------|----------------------------------|--------------------------------|\n| ! 警告       | 「死亡または重傷を負うことが想定される」内容です。 | 「警告や注意を促す」内容です。           |\n| ! 注意       | 「軽傷を負うことが想定されるか、または物的損害の発生が想定される」内容です。    | してはいけない「禁止」内容です。          |\n| ! (黒塗り)   |                                  | 実行していただく「指示」内容です。         |\n\n---\n\n## 火災や感電、けがなどを防ぐために  ⚠ 警告\n\n### 設置するとき\n\n- ![水ぬれ禁止アイコン] 屋外、水のかかるところや湿気の多いところに設置しない  \n  （絶縁が悪くなり感電・火災の原因）\n\n- ![アース線接続アイコン] 湿気の多い場所・水気のある場所に設置するときはアース（接地）・漏電遮断器を取り付ける →（P.7）  \n  （販売店にご相談ください）\n\n- ![必ず実施アイコン] 地震にそなえて転倒防止処置をする →（P.7）  \n  冷蔵庫の周囲はすき間をあけて設置する →（P.6）  \n  （冷媒が漏れると滞留し、発火・爆発のおそれ）\n\n---\n\n### 電源や電源プラグ・コードは（感電・発火・火災の原因）\n\n- ![禁止アイコン] ぬれた手で電源プラグを抜き差ししない  \n- ![禁止アイコン] 傷んだりコンセントの差し込みがゆるいときは使用しない  \n- ![禁止アイコン] 傷つけない  \n  （傷つけのおそれのある取り扱い例）  \n  ・加工する・束ねる・ねじる・引っ張る  \n  ・重い物をのせる・はさみ込む・無理に曲げる  \n  ・電源プラグを冷蔵庫で押しつける  \n\n- ![必ず実施アイコン] 交流100V、定格15A以上のコンセントを単独で使う  \n  （タコ足配線、延長コードは使用しない）  \n- ![必ず実施アイコン] コードを下向きに、電源プラグは根元まで確実に差し込む  \n- ![必ず実施アイコン] 必ず電源プラグを持って抜く  \n- ![必ず実施アイコン] お手入れの際は抜く →（P.23）  \n- ![禁止アイコン] 長期間使用しないときは抜く  \n- ![必ず実施アイコン] 定期的に電源プラグに付いたホコリを乾いた布でふき取る →（P.23）  \n\n---\n\n### ふだん ご使用のとき\n\n- ![禁止アイコン] 冷蔵庫本体や庫内に水やし尿をかけない  \n  （漏電・火災・感電の原因）\n\n- ![禁止アイコン] 冷蔵庫の上にもの、特に水を入れた容器を置かない  \n  （けが・発火のおそれ）\n\n- ![禁止アイコン] ドアや部品に無理な力をかけない  \n  （けがのおそれ）  \n  《無理な力がかかる例》  \n  ・ぶら下がる・乗る（開けたドアなど）  \n  ・寄りかかる・衝撃を加える  \n  ・ドアを大きく開けすぎる  \n\n- 自動製氷機の機械部には手を入れない（けがのおそれ）\n\n- 以下のものは収納しない  \n  ・薬品や学術試料  \n  （厳密な温度管理が必要なものは保存不可）  \n  ・引火しやすいもの（引火・爆発のおそれ）  \n  ・ドライアイス（袋等に入れると破裂するおそれ）\n\n- 庫内で電気製品を使用しない\n\n- 可燃性スプレーを近くで使わない\n\n- 霜取りを早く行うために機械的な器具、ドライヤーなどの熱器具または火気を使用しない\n\n- 分解・修理・改造は絶対にしない\n\n- 冷蔵庫本体にネジ等の鋭利なもので傷をつけない\n\n- 部品が破損した状態のまま使用しない  \n  （けが・感電・発火・火災のおそれ）\n\n---\n\n### もしものとき（発火・火災の原因）\n\n- ![必ず実施アイコン] 都市ガスなどの可燃性ガスが漏れたら、冷蔵庫やコンセントに触れず窓を開けて換気する\n\n- ![必ず実施アイコン] 以下のときは販売店に相談する  \n  ・側面や天面（冷却回路）を傷つけたとき  \n  （換気をし、電気製品の使用を避け、販売店に相談）  \n  ・震災や水害に遭ったとき  \n  （電源を入れる前に販売店に相談）  \n```\n",
    "metadata": {
      "topics": [
        "冷蔵庫の安全使用",
        "設置時の注意事項",
        "電源プラグの取り扱い",
        "日常使用時の注意点",
        "緊急時の対応"
      ],
      "keywords": [
        "冷蔵庫",
        "安全上のご注意",
        "感電防止",
        "火災予防",
        "電源プラグ",
        "アース（接地）",
        "転倒防止",
        "換気",
        "漏電遮断器",
        "可燃性ガス"
      ],
      "section_header": "安全上のご注意",
      "page_type": "safety"
    }
  },
  {
    "page": 5,
    "summary": "このページは冷蔵庫の火災、感電、けが防止のための注意事項を説明しています。廃棄・リサイクル時にはドアパッキングの取り外しやプラグを抜くことが重要で、食品の収納やドアの開閉、移動時には安全対策を徹底する必要があります。特にガラス棚の取り扱いや冷凍食品の注意、運搬時の注意点が詳細に記載されています。",
    "content": "```markdown\n# 火災や感電、けがなどを防ぐために\n\n## 警告\n\n### 廃棄・リサイクルするとき\n- ![必ず実施] リサイクルや保管するときは、必ずドアパッキングを取りはずす  \n  （幼児が閉じ込められるおそれ）  \n  ![図: ドアパッキングを外す様子]\n- 廃棄するときは、販売店や市町村に引き渡す  \n  （放置して冷媒が漏れると、引火・爆発の原因）\n\n### 異常・故障時には電源プラグを抜く\n- ![必ず実施] 直ちに使用を中止し、販売店へ点検・修理を依頼する  \n  《異常・故障の例》  \n  ・電源コード・プラグが異常に熱い、深い傷や変形がある  \n  ・焦げくさいにおいがする  \n  ・ピリピリと電気を感じる\n\n---\n\n# けがや事故などのおそれ\n\n## 注意\n\n### 食品を収納するとき\n- 禁止  \n  ・ガラス棚のガラス面を加熱したり、熱いものを置いたりしない  \n  ・ガラス棚に強い衝撃を加えない  \n    （ガラス棚が割れて、けがをするおそれ）  \n  ・ドアポケットの底面まで入らないボトル類は入れない  \n  ・食品をつめすぎたり、食品を棚より前に出さない  \n    （食品の落下・けがのおそれ）  \n  ・冷凍室にビン・缶類を入れない  \n    （中身が凍って割れて、けがをするおそれ）  \n  ・冷凍室の食品や容器（特に金属製）をぬれた手でさわらない  \n    （凍傷のおそれ）  \n  ・におったり、変色した食品は食べない  \n    （腐敗により病気になるおそれ）\n\n### ドアを開閉するとき（けがのおそれ）（つづき）\n- 注意  \n  ・ドアを開いたまま、ほかのドアを開閉する場合には、開いたドアとの間で手や指をはさまないよう十分注意する\n\n### お手入れのとき\n- 禁止  \n  ・冷蔵庫底面に手や足を入れない  \n    （けがのおそれ）  \n- 注意  \n  ・ガラス棚は重いため取り付け、取りはずしには十分注意する  \n    （棚が落下し、破損やけがのおそれ）\n\n### ドアを開閉するとき（けがのおそれ）\n- 禁止  \n  ・冷蔵庫ドアのハンドルに手をかけたまま引き出しドアを開閉しない  \n  ・最下段の引き出しドアに足を近づけすぎない  \n  ・ほかの人がさわっているときはドアを開閉しない  \n  ・ドアを強く開閉しない  \n    （食品が落下するおそれ）  \n- ![必ず実施] ドアはハンドルを持って開閉する  \n  （指をはさむおそれ）  \n- ![必ず実施] すき間が出来ないように確実にドアを閉める  \n  （床に結露水や霜取りの水が滴下するおそれ）  \n- 注意  \n  ドア開閉時の異常（異音や摩耗粉など）に気付いた場合は、使用をやめて点検を依頼する  \n  （部品の破損やそれによるけがのおそれ）\n\n### 移動・運搬・設置のとき→(P.33)\n- 禁止  \n  ・横積み輸送はしない  \n    （故障の原因）  \n  ・ドアのハンドルを運搬時に使用しない  \n    （手がすべり、けがの原因）  \n  ・傷つきやすい床の上では冷蔵庫を引きずらない  \n    （床を傷つける原因）  \n- ![必ず実施]  \n  ・保護用のシート・布などを敷く  \n    （床の傷つきのおそれ）  \n  ・食品や氷を取り出し、給水タンクの水をすてる  \n  ・ドアが開かないよう、テープなどで固定する  \n  ・電源プラグやコードがたれ下がらないよう、テープで固定する  \n    （運搬中の事故・けがの原因）  \n  ・運搬用取っ手を持って２人以上で運ぶ  \n    （手がすべり、けがの原因）  \n  ・床が丈夫で水平なところに調節脚でしっかり固定する  \n    （冷蔵庫の転倒・けがの原因）  \n  ![図: 運搬用取っ手を持って運搬する様子]\n```\n",
    "metadata": {
      "topics": [
        "廃棄・リサイクル時の安全対策",
        "異常時の電源プラグの取り扱い",
        "食品の安全な収納方法",
        "ドアの開閉時のけが防止",
        "冷蔵庫の移動・運搬・設置の注意点"
      ],
      "keywords": [
        "火災防止",
        "感電防止",
        "けが防止",
        "ドアパッキング取り外し",
        "電源プラグ抜く",
        "ガラス棚",
        "冷凍室",
        "凍傷",
        "運搬用取っ手",
        "調節脚"
      ],
      "section_header": "安全",
      "page_type": "safety"
    }
  },
  {
    "page": 6,
    "summary": "このページは冷蔵庫の設置場所の条件と、水平調整の手順を詳しく説明しています。床の材質や設置環境に注意しながら、脚カバーの脱着や調節脚の回し方を図解で解説し、ドアの平行調整のコツや注意点も記載しています。",
    "content": "```markdown\n# 準備する  \n## 使いはじめるまでの手順\n\n### 1 次のような場所に設置する\n- 床が丈夫で、水平方なところ  \n　じゅうたん、畳、フローリング、塩化ビニール などの床が変形、変色するおそれがある場合は板（1cm厚以上）を敷いてください。  \n- 熱気・直射日光が少ないところ  \n　冷却力の低下や、電気代の増加をおさえます。  \n- 湿気が少なく、風通しの良いところ  \n　さびや結露をおさえます。  \n- テレビなどから離れたところ  \n　雑音や映像の乱れを防止します。  \n- 放熱スペースをあけてください。（右図）  \n　※本体側面中央部は表示寸法より大きめになる場合があります。余裕を持って設置してください。  \n　※振動音や、湿気が多いときの背面の結露、壁や壁紙の変色汚れが気になるときは、壁から離して（2cm以上）ください。\n\n![図: 上部 5cm以上、左右 0.5cm以上の放熱スペースの説明図]\n\n---\n\n### 2 冷蔵庫を水平に調整・固定する\n\n#### 1 脚カバーを持って、手前に引いて取りはずす\n\n![図: 脚カバーを手前に引いて取りはずすイラスト]  \n脚カバー\n\n#### 2 左右の調節脚を床に付くまで回す  \n冷蔵室ドアが平行になるように調整する  \n調節脚を回す量は、ドアの下がり1mmにつき1回転を目安にしてください。調節脚が回しにくいときは、プラスドライバーを差し込んで回してください。\n\n| 右側が下がっている               | 左側が下がっている               |\n|-------------------------|-------------------------|\n| 左の調節脚を時計回りに回して下げる  | 右の調節脚を時計回りに回して下げる  |\n\n- 調節脚を回す際に、プラスドライバーで床面を傷つけないようにご注意ください。  \n- 調節脚を回しすぎると調節脚がはずれる場合があります。\n\n![図: 調節脚、プラスドライバーの使用イラスト]\n\n#### プラスドライバーのサイズの目安\n- 長さ：約10cm  \n- 差し込み幅：約0.6cm  \n\nプラスドライバーは調節脚の溝部分にしっかりと差し込み、回してください。\n\n![図: プラスドライバーのサイズの目安イラスト]\n\n#### 3 脚カバーのつめを取り付け穴に差し込み、取り付ける\n\n![図: 脚カバーのつめを取り付け穴に差し込むイラスト]  \n脚カバー  \nつめ  \n取り付け穴\n\n---\n\n### お知らせ\n- 床材の強さや材質、食品の重みによって数日後（5日程度）にドアが下がることがあります。そのときは、もう一度ドアの平行調整をしてください。  \n- 冷蔵庫の設置する場所が水平でなかったり、床材がやわらかいときは、冷蔵室ドアが傾く場合があります。機能上問題ありませんが、気になる場合は左記の手順でドアの平行調整を行ってください。  \n- 左右水平にし、冷蔵庫の前側をやや上げ気味に調整するとドアが閉まりやすくなり半ドアになりにくくなります。  \n- 冷蔵室ドアを開いた状態で手をはなしたとき、ドアが動く場合がありますが、故障ではありません。  \n- 調節脚を回してもドアの平行が直らない場合は、調整板（別売部品）をお使いください。（→P.35）\n```\n",
    "metadata": {
      "topics": [
        "冷蔵庫の設置場所の条件",
        "冷蔵庫の水平調整方法",
        "調節脚の操作方法",
        "脚カバーの取り外しと取り付け",
        "調整時の注意事項"
      ],
      "keywords": [
        "冷蔵庫",
        "設置場所",
        "水平調整",
        "調節脚",
        "脚カバー",
        "プラスドライバー",
        "放熱スペース",
        "床材",
        "ドア平行調整",
        "調整板"
      ],
      "section_header": "準備する",
      "page_type": "instruction"
    }
  },
  {
    "page": 7,
    "summary": "このページでは冷蔵庫の庫内清掃方法や電源プラグの差し込み方、冷却開始の注意点を説明しています。また、感電防止のためのアース接続の重要性や設置環境に関する注意事項、地震対策としての転倒防止ベルトの使用についても触れています。",
    "content": "```markdown\n# 3 庫内を掃除する →(P.23〜25)\n- 湿らせたやわらかい布でふいたあと、乾いた布で仕上げてください。\n- 給水タンクや浄水フィルターを水洗いしてください。  \n※引き出しレールやレールの接触面に塗られている潤滑剤は、ふき取らないでください。  \n　（潤滑剤は、食品衛生法に適合しています）  \n※使いはじめは、プラスチックのにおいがする場合があります。  \n　気になるときは、においがこもらないように部屋の風通しをよくしてください。（においは次第に消えます）\n\n# 4 電源プラグを差し込む\n設置後、すぐに電源プラグを差し込んでも問題ありません。  \nコンセントは単独で使用してください。（交流100V、定格15A以上）  \n- 電源プラグやコードが冷蔵庫背面と壁との間にはさまれていないか確認してください。コードの発熱を防ぎます。\n\n## 庫内の冷却がはじまります（冷蔵室と他の貯蔵室（製氷室・冷凍室・野菜室）を交互に冷やします）  \n- 冷蔵庫の周囲の温度や、食品の収納状態によって庫内が十分に**冷えるまでに24時間以上**かかることがあります。  \n　アイスクリームや冷えていない食品、傷みやすい食品は庫内が十分冷えるまで入れないでください。  \n- はじめて自動製氷をお使いのときは、手順に従い自動製氷機の「製氷おそうじ」をしてください。→(P.25)  \n- 製氷運転は庫内が十分冷えてから開始されます。  \n　（使いはじめは、**最初の氷ができるまでに24時間以上**かかることもあります）  \n- 庫内温度が低いときなどは電源プラグを差し込んでから10分程度冷却が始まらないことがあります。\n\n## 万一の感電防止のためにアース（接地）をおすすめします。\n- アース線（お買い上げの販売店などでお買い求めください）をコンセントのアース端子と背面左下のアース取り付けねじに接続してください。  \n\n```\nアース取り付けねじ ── アース端子  \n　　　　　　　　│  \nアース線（銅線直径1.6mm）  \n```\n\n- ※コンセントにアース端子がないときは、お買い上げの販売店などにアース工事（別料金）を依頼してください。  \n- ※湿気の多い場所・水気のある場所（土間など）に設置するときは、必ずアースを取り付けてください。また、アースの他に漏電遮断器の設置が義務付けられています。お買い上げの販売店にご相談ください。\n\n### アース線を接続してはならないところ\n- 水道管（感電の危険）  \n- ガス管（爆発の危険）  \n- 電話線や避雷針のアース（落雷のとき危険）  \n※法令などで禁止されています。\n\n---\n\n## お知らせ\n- 配管の防さび処理が必要となる場合があります。  \n　温泉地域や工業地域周辺、下水配管の近くなどに冷蔵庫を設置する場合、硫化ガスの影響で配管が腐食することがあります。販売店にご相談ください。なお、配管が黒く変色する等、ガス害による故障は保証の対象外となります。  \n- 電源プラグを差し込んだ後、運転音がします。また、冷蔵庫が十分に冷えるまで、コンプレッサーやファンの音が大きいと感じることがあります。  \n- 背面のシールをはがしたり、側面下部のプラスチック部品をはずさないでください。  \n- マグネットや吸盤を本体やドアの表面に付けた場合、跡が残る場合があります。  \n- 周囲の湿度が高いとき、ドア表面に紙などを貼ると、ドア表面に露がついたり、紙が吸湿する場合があります。  \n\n```\n[図: シールとプラスチック部品（左右）イラスト]\n```\n\n---\n\n# 地震にそなえて\n地震に備えるため冷蔵庫用地震転倒防止ベルト（別売部品）を2セット使用し、丈夫な壁や柱に固定していただくことをおすすめします。→(P.35)  \n\n```\n[図: ネジ４本（ベルトに同梱）とベルトのイラスト]\n```\n```",
    "metadata": {
      "topics": [
        "庫内の掃除方法",
        "電源プラグの接続と注意点",
        "庫内冷却の開始と自動製氷の注意",
        "アース接続の推奨と注意事項",
        "設置時の注意点と地震対策"
      ],
      "keywords": [
        "給水タンク",
        "浄水フィルター",
        "潤滑剤",
        "冷凍室",
        "自動製氷",
        "アース線",
        "接地",
        "地震転倒防止ベルト",
        "漏電遮断器",
        "硫化ガス"
      ],
      "section_header": "設置・準備",
      "page_type": "instruction"
    }
  },
  {
    "page": 8,
    "summary": "このページでは、冷蔵庫の操作パネルの機能や節電設定、冷凍・冷蔵室の温度調節方法について説明しています。また、操作時の注意点やお知らせ、さらに冷蔵庫の各部屋の名称を紹介しています。",
    "content": "```markdown\n# 確認する\n\n## 操作パネルのはたらき\n\n| 製氷                                         | 冷却モード                         |\n|----------------------------------------------|----------------------------------|\n| ● 急速製氷→(P.15)                           | ● 急冷凍　→(P.17)               |\n| ● 製氷　　→(P.14)                           | ● クイック冷却→(P.11)            |\n| ● 製氷停止→(P.15)                           |                                  |\n\n- 節電  \n  各室の冷却を少し弱めて節電します。  \n  ● 節電→(P.22)\n\n- 冷凍・冷蔵  \n  冷凍室、冷蔵室の庫内温度を3段階に調節できます。  \n  ● 温度の調節→(P.10,17)\n\n### お願い\n\n操作パネルには強い衝撃を与えたり、硬いものを当てたりしないでください。\n\n### お知らせ\n\n- 「冷却モード」は、「急冷凍」または「クイック冷却」のどちらか一方をお選びいただけます。  \n- 操作パネルのランプが点滅しているときは→(P.30)  \n- 「点字シール」をご用意しています。  \nパネルに貼り付けていただくと、ボタンの位置と操作内容がわかるようになります。  \n\nご希望の方は、商品情報や使い方に関するご相談窓口へご連絡をお願いします。→(P.35)\n\n\n---\n\n## 各室のなまえ\n\n- 冷蔵室\n- 特鮮氷温ルーム\n- 製氷室\n- 冷凍室上段\n- 冷凍室下段\n- 野菜室\n\n[図: 冷蔵庫の各部屋の名称]\n```",
    "metadata": {
      "topics": [
        "操作パネルの機能",
        "製氷機能",
        "冷却モード",
        "節電機能",
        "冷蔵庫の各室名称"
      ],
      "keywords": [
        "急速製氷",
        "製氷停止",
        "急冷凍",
        "クイック冷却",
        "節電",
        "庫内温度調節",
        "操作パネル",
        "点字シール",
        "冷蔵室",
        "野菜室"
      ],
      "section_header": "確認する",
      "page_type": "instruction"
    }
  },
  {
    "page": 9,
    "summary": "このページでは、冷蔵庫内の各保存場所ごとの温度目安と適した食品例を示しています。冷蔵室、製氷室、冷凍室、野菜室それぞれの最適温度帯と保存食品を具体的に紹介し、食品の保管時のコツや注意点も説明しています。温度目安は標準条件下の参考値であることも記載されています。",
    "content": "```markdown\n# 保存食品例\n\n| 保存場所 | 温度の目安 | 食品 |\n| --- | --- | --- |\n| **冷蔵室** →(P.10) ※「チルド」設定のとき | 棚 | 約0℃～3℃ |  \n| | | **日常的に使う食品**  \n| | | サラダ、ケーキ、豆腐、乳酸菌飲料、プリン |\n| | ドアポケット | 約0℃～7℃ |  \n| | | 鍋に入れた食品、生卵、調味料、ビール、牛乳、ペットボトル、バター、チーズ、カットした果物 |\n| | 特鮮氷温ルーム →(P.13) | 約－2℃～0℃ |  \n| | | **肉・魚介類など生鮮食品**  \n| | | 肉、魚介類、かまぼこ、ちくわ、ウインナー |\n\n| **製氷室** →(P.14) | | 約－19℃～－17℃ |  \n| | | 自動製氷でつくった氷  \nそれ以外の氷や食品は入れないでください。 |\n\n| **冷凍室** →(P.16) ※「標準」設定のとき | 冷凍室上段 | 約－19℃～－17℃ |  \n| | | コーヒー豆、茶葉、うどん、食パン |\n| | 冷凍室下段 | 約－20℃～－18℃ |  \n| | | 肉・魚介類、アイスクリーム、冷凍食品、ごはん |\n\n| **野菜室** →(P.18) | 上段・下段スペース | 約4℃～8℃ |  \n| | | **上段スペース**  \n小物野菜や使いかけの野菜、果物など  \nトマト、イチゴ、グレープフルーツ、ピーマン、しいたけ |\n| | | **下段スペース**  \n葉物野菜、大物野菜など  \nホウレンソウ、小松菜、キャベツ、レタス |\n\n| | たて収納スペース | 約4℃～9℃ |  \n| | | **たて収納スペース**  \n背の高い野菜やペットボトルなど  \nきゅうり、アスパラガス、ペットボトル |\n\n---\n\n### 保存のコツ\n- 食品はすき間をあけて収納してください。\n- においの強い食品はラップをすることをおすすめします。\n- 収納できる食品の重さの目安があります。→(P.34)\n\n---\n\n※温度の目安は、ご購入時の庫内温度の設定で、冷蔵庫の周囲温度約32℃で食品を入れずにドアを閉め、温度が安定したときの目安です。  \n※食品の収納状態やドアの開閉などにより、温度が変動する場合があります。\n```",
    "metadata": {
      "topics": [
        "冷蔵庫の保存場所別温度目安",
        "保存食品の種類",
        "保存のコツ",
        "保存温度の注意点"
      ],
      "keywords": [
        "冷蔵室",
        "製氷室",
        "冷凍室",
        "野菜室",
        "チルド",
        "特鮮氷温ルーム",
        "食品保存温度",
        "氷温",
        "温度目安",
        "食品の保存方法"
      ],
      "section_header": "保存食品例",
      "page_type": "instruction"
    }
  },
  {
    "page": 10,
    "summary": "このページは冷蔵室の各部の名称や使用上の注意点を説明しています。特に「まるごとチルド」設定の特徴と温度調整方法、冷蔵室内での食品の適切な保存方法について詳述しています。",
    "content": "```markdown\n# 冷蔵室\n\nうるおい冷蔵室は、たっぷりのうるおい冷気で食品を保存します。\n\n## 各部のなまえ\n\n- LED庫内灯\n- 高さかわるん棚 上段・中段\n- 小物ケース（卵スタンド付き）\n- 固定棚\n- 冷気吹き出し口\n- 高さかわるポケット\n- ポケット\n- 高さかわるん棚 下段\n- ダブルポケット\n- ハンドル\n\n---\n\n### お願い\n- 水分が多い食品や缶飲料は、冷気吹き出し口の前に置くと凍ったり破裂するおそれがあるので、冷気吹き出し口の前に置かないでください。特に「チルド」設定時はより凍りやすくなります。蓋やラップをすることで食品の凍結を抑えることができます。\n- 米、海苔などの乾燥食品を収納する際は、密閉した容器（袋）に入れてから収納してください。乾燥食品が吸湿することがあります。\n- 温かい食品を保存したときやドア開閉をしたときに、食品や空気中にふくまれる水分により冷蔵室内に露がつくことがあります。気になる場合は乾いた布でふき取ってください。\n\n---\n\n## 「まるごとチルド」を使う\n\n※ご購入時は、「まるごとチルド」に設定されています。\n\n- 冷蔵室全段をより低温にします。（設定時：約0～3℃）  \n  作り置きの総菜などの保存におすすめです。  \n  温かい食品を保存するときは、**手で持てるくらいの温度（50℃以下）に冷まし**てから入れてください。やけどや棚の変形を防ぎます。\n- 「まるごとチルド」に設定されているかは操作パネルで確認できます。  \n  「チルド」ランプが点灯している間は「まるごとチルド」の設定になっています。\n\n### お知らせ\n- 「まるごとチルド」設定時は、「標準」よりも消費電力量が多くなります。  \n  また、運転音が大きくなることがあります。\n- 「まるごとチルド」設定時は、ポケットの温度も「標準」より低くなります。\n\n---\n\n## 変更するとき\n\n### 冷蔵を押して温度の変更をする\n\n冷えすぎると感じるときは、「標準」または「弱め」でお使いください。\n\n#### 冷蔵室温度の目安\n- 「標準」は「チルド」より約1～3℃高め\n- 「弱め」は「標準」より約1～3℃高め\n\n---\n\n■操作パネルの説明\n\n| チルド | 標準 | 弱め | 冷蔵 |\n|--------|------|-------|------|\n| 点灯   | 点灯 | 点灯  |      |\n| 押す   | 押す | 押す  |      |\n\n[図: 冷蔵室の構成と操作パネルの説明]\n\nまるごとチルドスペース\n```\n",
    "metadata": {
      "topics": [
        "冷蔵室の各部名称",
        "食品保存時の注意点",
        "まるごとチルド機能の概要",
        "冷蔵室温度設定の変更方法",
        "操作パネルの説明"
      ],
      "keywords": [
        "冷蔵室",
        "うるおい冷蔵室",
        "まるごとチルド",
        "チルド設定",
        "冷気吹き出し口",
        "食品の冷凍防止",
        "温度設定",
        "操作パネル",
        "消費電力量",
        "保存温度 0～3℃"
      ],
      "section_header": "冷蔵室",
      "page_type": "instruction"
    }
  },
  {
    "page": 11,
    "summary": "このページは冷蔵庫の「クイック冷却」機能の使い方を説明しており、温かい食品を速く冷やすための設定方法や注意点を紹介しています。また、食品や飲料に合わせてポケットや棚の高さを調節する方法と、その取り扱いの注意点についても解説しています。",
    "content": "```markdown\n# 食品を急いで冷やしたいとき（「クイック冷却」を使う）\n\n食品を急いで冷やしたいときに、「まるごとチルドスペース」の冷却を強める運転をします。  \n温かい食品の冷却および加熱調理後のあら熱とりの時間を短縮できます。  \nお出かけ前のお弁当、飲料、加熱調理後の野菜などをすばやく冷やしたいときにおすすめです。  \n温かい食品を収納するときは**手で持てるくらいの温度（50℃以下）に冷ましてから入れてください。**  \nやけどや棚の変形を防ぎます。\n\n---\n\n## 設定するとき\n\nご購入時は、「切」に設定されています。\n\n**冷却モード** を押して「クイック冷却」ランプを点灯させる  \n約60分で運転を自動終了し、「クイック冷却」ランプが消灯します。  \n冷蔵室の温度によっては60分以上運転することがあります。\n\n---\n\n## 途中で解除するとき\n\n**冷却モード** を押してランプを消灯させる\n\n### お知らせ  \n- 「クイック冷却」と「急冷凍」は同時には設定できません。  \n- 「クイック冷却」設定時は、解除時よりも消費電力量が多くなります。  \n- 「クイック冷却」を連続で使用すると庫内の食品が凍結する場合があります。  \n- 「まるごとチルド」設定中でも使用できます。\n\n---\n\n# ポケット・棚の高さをかえる\n\n食品や飲料の大きさにあわせてポケットや棚の位置をかえることができます。  \n取りはずしかた・取り付けかた →（P.26）\n\n> ⚠️ 注意  \n> ■ ガラス棚を取り扱う場合  \n> ・ガラス棚に強い衝撃を加えない（ガラス棚が割れてけがをするおそれ）  \n> ・ガラス棚は重いため取り付け、取りはずしには十分注意する\n\n---\n\n## ■ 高さかわるん棚上段・高さかわるん棚中段・高さかわるるポケット  \n食品や飲料の高さに応じて、調節できます。\n\n[冷蔵室の食品収納スペースの目安 →（P.34）は下記の配置で算出しています。]\n\n| 高さかわるん棚上段 | 上から2段目 |  \n|---|---|  \n| 高さかわるん棚中段 | 上から4段目 |  \n| 高さかわるん棚下段 | 上段 →（下記参照） |  \n| 高さかわるんポケット | 下段 |  \n\n---\n\n## ■ 高さかわるん棚下段  \n3段階に調節できます。\n\n- ご購入時の状態（上段）\n- なべの収納など（中段）\n- 牛乳パックの収納など（下段）\n\n---\n\n[図]  \n- まるごとチルドスペースの場所を示す冷蔵庫の断面図\n- 操作パネルの「冷却モード」ボタンの説明（「急冷凍」・「クイック冷却」のランプ点灯状態）\n- ポケット・棚の高さ変更イメージ（上段・中段・下段のイラスト）\n- 棚の高さ変更の仕組みの図解（冷蔵庫内棚の高さ位置示す図）\n```\n",
    "metadata": {
      "topics": [
        "クイック冷却機能の使い方",
        "冷却モードの設定と解除",
        "クイック冷却の注意事項",
        "ポケット・棚の高さ調節方法",
        "安全な棚の取り扱い"
      ],
      "keywords": [
        "クイック冷却",
        "まるごとチルドスペース",
        "冷却モード",
        "急冷凍",
        "消費電力量",
        "棚の高さ調節",
        "ガラス棚",
        "食品冷却",
        "冷蔵庫",
        "60分運転"
      ],
      "section_header": "使い方・設定",
      "page_type": "instruction"
    }
  },
  {
    "page": 12,
    "summary": "このページは冷蔵室内で小物ケースや卵スタンドを使って食品を収納する方法を説明しています。卵スタンドは小物ケースとしても使え、取り扱い時の注意点や設置場所のポイントも記載されています。食品の安全な収納のために、氷作り禁止や冷気吹き出し口から離して使うことが推奨されています。",
    "content": "```markdown\n# 冷蔵室 ～つづき～\n\n## 小物ケースを使う\n\n小物や卵などを入れて、冷蔵室内に置くことができます。  \n卵スタンドを使うと卵を14個収納できます。  \n卵パックのまま収納することもできます。\n\n- 小物ケース  \n- 卵スタンド  \n\n卵スタンドを裏返すと小物食品を入れることができます。\n\n- 小物ケース  \n- 卵スタンド  \n\n卵スタンドはポケットに置いて使うこともできます。\n\n---\n\n### お願い\n\n- 取り扱いはケースをしっかりと持って行ってください。  \n- 落下する可能性があるので、食品は積み重ねて収納しないでください。  \n- このケースで氷をつくらないでください。（ケースが破損するおそれ）  \n- 冷気吹き出し口付近に置くと、食品が凍結したり破裂したりするおそれがあります。  \n　冷気吹き出し口付近からはなれた位置でご使用ください。  \n- 棚より前にだして置かないでください。  \n- 収納する食品の高さに注意してください。（食品が落下するおそれ）\n\n---\n\n### 図解\n\n- 冷蔵室の中のポケットに卵スタンドをセット  \n- 卵スタンドはポケットの右側にセットしてください。\n\n```\n[図：冷蔵室内のポケットと卵スタンドの位置を示す図]\n```\n```",
    "metadata": {
      "topics": [
        "冷蔵室の小物収納",
        "卵スタンドの使い方",
        "収納上の注意点",
        "冷気による凍結防止",
        "設置場所の指示"
      ],
      "keywords": [
        "小物ケース",
        "卵スタンド",
        "冷蔵室",
        "卵収納",
        "食品収納",
        "冷気吹き出し口",
        "凍結防止",
        "落下防止",
        "収納高さ",
        "卵パック"
      ],
      "section_header": "冷蔵室",
      "page_type": "instruction"
    }
  },
  {
    "page": 13,
    "summary": "特鮮氷温ルームは約−2℃〜0℃で肉類や魚介類の鮮度と栄養素を守って保存できる冷蔵スペースです。水分の多い食品は凍結する場合があり、一部の食品（乳製品やカット野菜など）は凍結に向かないため冷蔵室での保存が推奨されます。特鮮氷温ケースの正しい開閉方法や使用上の注意点、水滴や霜の取り扱い方法も説明されています。",
    "content": "```markdown\n# 特鮮氷温ルーム\n鮮度と栄養素を守っておいしく保存できます。\n\n![特鮮氷温ルーム](画像内: 特鮮氷温ルームイラスト)\n\n## 収納食品\n\n| 特鮮氷温ルーム (約−2℃〜0℃) | 内容例 |\n|---|---|\n| ● 肉類・肉の加工品 | 牛肉・豚肉・鶏肉・ハム・ソーセージなど |\n| ● 魚介類・海産物・魚の加工品 | サバ・ブリ・アジ・イクラ・練り物など |\n| ● 肉や魚の解凍 | ・水分の多い食品は凍る場合があります。 |\n\n---\n\n## ご注意\n- 周囲温度が低いとき、水分の多い食品は凍ることがあります。\n- 冷蔵室・冷凍室の温度設定を変更すると、特鮮氷温ルームの温度も変動します。\n- **特鮮氷温ルームには、食品や容器を無理に詰め込まないでください。**  \n  特鮮氷温ケースを引き出すことができなくなることがあります。\n\n---\n\n## 特鮮氷温ルームに向かない食品\n以下の食品は、凍結が苦手です。冷蔵室で保存してください。\n\n- **乳製品**  \n  チーズなど\n- **カットした野菜や果物**  \n  カットした生野菜、カットした果物\n- **凍るとスが入るもの**  \n  豆腐、こんにゃく、厚揚げ、しらたき、ゆで卵など\n\n---\n\n# 特鮮氷温ケースを開閉する\n\n### 開けるとき\nハンドルを持って特鮮氷温ケースを手前に引き出す  \n![開ける動作の図](画像内: ハンドルを持って引き出すイラスト)\n\n### 閉めるとき\n特鮮氷温ケースを奥まで押し込む  \n![閉める動作の図](画像内: 奥まで押し込むイラスト)\n\n※奥まで押し込んでから冷蔵室ドアを閉めてください。\n\n---\n\n## ご注意\n- 特鮮氷温ケースを奥まで押し込まずに冷蔵室ドアを閉めると部品や食品などが破損したり、ドアにすき間ができ冷えが悪いなどの原因になります。\n\n---\n\n## お願い\n- 食品や空気中にふくまれる水分により、ルーム内に水滴や霜、氷がつくことがあります。やわらかい布にぬるま湯をふくませてふき取ってください。（水滴や霜、氷がついても性能に支障ありません）\n- 水滴や霜、氷が気になる場合は、収納食品にラップすることをおすすめします。\n- ルーム内に水や食品の汁をこぼした場合は、すぐにふき取ってください。→（P.24）\n- 食品の包装がはさまったときは、取り除いてください。\n- 特鮮氷温ケースを開けている最中に、ドアに重いものを乗せないでください。\n- ドア表面の透明部分には保護フィルムが差し込んであります。  \n  そのままご使用されても性能に支障ありませんが、気になる場合ははずしてご使用ください。\n\n---\n\n### 保護フィルムのはずし方\n保護フィルムをはずすときは絵のように端から中央に向けてフィルムをひき、はずしてください。\n\n---\n\n## イラスト説明\n- 特鮮氷温ケース  \n- ハンドル  \n- ドア  \n- 水滴や霜、氷  \n- 保護フィルムはずしの動作図\n\n---\n\nページ番号: 13\n```",
    "metadata": {
      "topics": [
        "特鮮氷温ルームの特徴",
        "収納可能な食品と保存温度",
        "開閉方法と使用上の注意",
        "凍結に向かない食品",
        "保護フィルムの取り扱い"
      ],
      "keywords": [
        "特鮮氷温ルーム",
        "−2℃〜0℃",
        "肉類",
        "魚介類",
        "凍結",
        "保存方法",
        "冷蔵室",
        "冷凍室",
        "保護フィルム",
        "水滴・霜・氷"
      ],
      "section_header": "特鮮氷温ルーム",
      "page_type": "instruction"
    }
  },
  {
    "page": 14,
    "summary": "このページでは自動製氷機の使い方を解説しています。給水タンクへの水の補充から製氷の開始方法、注意点や推奨される水の種類、避けるべき使用水が詳しく説明されています。また、定期的な給水タンクの清掃と製氷おそうじの重要性も触れられています。",
    "content": "```markdown\n# 製氷室（自動製氷機）\n\n自動で氷をつくります。\n\n---\n\n### 図解\n\n- 操作パネル  \n  「製氷」ボタン  \n  - 急速製氷  \n  - 製氷  \n  - 製氷停止  \n  ※製氷おそうじ（5秒押し）\n\n- 給水タンク（容量 約1.0L）  \n  ※満水線\n\n- 製氷室  \n- ハンドル\n\n- 自動製氷機\n\n- 製氷ケース  \n  - 満水線  \n  - 貯氷スペース  \n  - 製氷スコップ（使用後はこの場所に戻してください）\n\n---\n\n# 氷をつくる（製氷）\n\nはじめて氷をつくるときや、1週間以上氷をつくらなかったときは、「製氷おそうじ」をしてください。→（P.25）\n\n---\n\n## 1. 「製氷」を押して「製氷」ランプを点灯させる\n\n- ご購入時は、「入」（点灯）に設定されています。\n\n---\n\n## 2. 給水タンクを水平に引き出す\n\n- 給水タンクを持ち上げて手前に引くと重く感じる場合があります。\n\n---\n\n## 3. 給水カバーを開けて水を入れる\n\n- ※満水線以上は水を入れないでください。\n\n---\n\n## 4. 給水タンクをセットする\n\n- 「タンクセット位置」の線を越えるように、奥までしっかりと押し込んでください。  \n- 給水タンクが奥まで押し込まれていないと、氷ができません。  \n- ※給水タンクを傾けると水がこぼれることがあります。水がこぼれたときは、すぐにふき取ってください。\n\n---\n\n## 5. 自動で製氷運転が始まります\n\n- 製氷ケースの満水線まで水がたまると、自動製氷機能が一時停止します。氷が少なくなると自動で再開します。  \n- 製氷ケース内に氷がないときは、製氷皿から氷が落ちる音が大きく聞こえることがあります。\n\n---\n\n## お願い\n\n- 水道水での製氷をおすすめします。  \n- 給水タンクは1週間に1回以上水洗いしてください。→（P.24）\n\n---\n\n### 注意事項\n\n- ミネラルウォーター、井戸水、浄水器の水、湯冷ましなど（塩素を含まない水）で製氷する場合は、こまめに給水タンクを洗ってください。ぬめりや雑菌の発生をおさえます。  \n- ミネラル成分の多い水でつくった氷を水に入れると、白い浮遊物（ミネラル成分）がでることがありますが、害はありません。\n\n---\n\n### 使用して良い水の例\n\n- ミネラルウォーター（硬度:100mg/L以下）  \n- 浄水器の水  \n- 井戸水（水質基準を満足するもの）\n\n---\n\n### 使用しないでください\n\n- 水以外のものを使用しないでください。  \n- 故障や、変形、氷のくっつきなどの原因になります。\n\n- ジュース類  \n- スポーツドリンク  \n- 炭酸飲料  \n- お茶\n\n---\n\n## お知らせ\n\n- 浄水フィルターの中には活性炭が入っているため、外側の不織布が濡れると中の活性炭が透けて見えることがあります。\n\n---\n\n### 浄水フィルターイメージ\n```",
    "metadata": {
      "topics": [
        "自動製氷機の操作方法",
        "給水タンクの取り扱い",
        "製氷に適した水の種類",
        "製氷機のメンテナンス",
        "安全注意事項"
      ],
      "keywords": [
        "自動製氷機",
        "製氷室",
        "給水タンク",
        "製氷おそうじ",
        "満水線",
        "ミネラルウォーター",
        "浄水器の水",
        "急速製氷",
        "製氷停止",
        "製氷ケース"
      ],
      "section_header": "製氷室（自動製氷機）",
      "page_type": "instruction"
    }
  },
  {
    "page": 15,
    "summary": "このページでは、冷蔵庫の製氷機について、氷の収納量や製氷時間、急速製氷の使い方が説明されています。また、氷が部分的にたまると製氷が停止することや、製氷停止時の注意点、製氷室内の整理や掃除の必要性についても案内しています。さらに、操作パネルのランプの意味や製氷に関連するトラブル対処法も示しています。",
    "content": "```markdown\n# 氷の収納量・製氷時間\n\n| 型式                     | R-HWS47X・R-HWS47XL                 |\n|--------------------------|------------------------------------|\n| 氷の収納量               | 約140個                           |\n| 1回（12個）の製氷時間   | 通常の「製氷」 約110分～140分       |\n|                          | 「急速製氷」 約80分                 |\n\n※周囲温度約30℃、冷凍室温度設定「標準」、冷蔵室温度設定「チルド」、ドア開閉なしのときの目安値です。\n\n---\n\n## お知らせ\n\n- 氷が部分的にたまると、氷が少ない状態でも製氷が停止することがあります。\n\n  ```\n  検知レバーに氷があたる\n          ↓\n  氷が少ない状態でも製氷が停止する\n  ```\n  氷（部分的にたまっている）\n\n- 氷を手前に寄せ、平らにならすことによりより多くの氷をつくることができます。\n\n  ```\n  より多くの氷をつくることができる\n  ```\n  氷（平らにならしている）\n\n- 次のようなときは、氷ができるまでの時間が長くかかります。\n  - はじめてお使いのとき（24時間以上かかることがあります）\n  - 冷凍室の温度設定が「弱め」のとき\n  - 冷蔵庫に大量の食品を一度に入れたとき\n  - 「節電モード」に設定しているとき\n\n---\n\n## お願い\n\n- 貯氷スペースには、自動製氷機でつくった氷以外の冷凍食品や製氷スコップなどを入れないでください。氷ができなくなったりします。（製氷機の部品が食品にあたったり、ドアが開かなくなったり、部品が破損することがあります）\n- 製氷室のドアは、ゆっくりと開閉してください。勢いよく開閉すると、製氷ケースから氷がこぼれ、冷凍室下段に落ちることがあります。\n\n---\n\n## 急いで氷をつくる（急速製氷）\n\n### 製氷を押して「急速製氷」ランプを点灯させる\n\n約7時間で運転を自動終了し、「製氷」に切り替わります。\n\n### 操作パネル\n\n- 急速製氷（点灯）\n- 製氷\n- 製氷停止\n- 製氷\n- おそうじ（5秒押し）\n\n### お知らせ\n\n- 「急速製氷」運転中は「急速製氷」ランプが点灯しつづけます。\n- 「急速製氷」運転時は冷凍室を優先して冷却しますので、冷蔵室のドア開閉が多いときなど冷蔵室の温度が上がりやすくなります。\n\n---\n\n## 氷をつくらない（製氷停止）\n\n### 製氷を押して「製氷停止」ランプを点灯させる\n\n※1週間以上「製氷停止」にするときは「製氷おそうじ」をしてください。→（P.24、25）\n\n### 操作パネル\n\n- 急速製氷\n- 製氷\n- 製氷停止（赤色点灯）\n- 製氷\n- おそうじ（5秒押し）\n\n---\n\n## 「製氷」または、冷凍「強め・弱め」と冷蔵「弱め」のランプが点滅しているとき\n\n製氷皿が製氷ケース内の食品にあたっている可能性があります。\n\n一度製氷ケース内を空にして、「製氷おそうじ」をしてください。→（P.25）\n\n### 操作パネル例1\n\n- 急速製氷\n- 製氷（点滅）\n- 製氷停止\n- 製氷\n- おそうじ（5秒押し）\n\nまたは\n\n### 操作パネル例2\n\n- 強め（点滅）\n- 標準\n- 弱め（点滅）\n- チルド（点滅）\n- 冷凍（点滅）\n- 冷蔵（弱め点滅）\n\n---\n\n### 図・イラスト内容\n\n- 検知レバーに氷があたる様子の図\n- 氷を手前に寄せて平らにする様子の図\n- 冷凍食品が冷凍室に入っていないかと製氷スコップの位置確認の図\n- 急速製氷、製氷停止の操作パネルの絵表示\n\n---\n\n15\n```\n",
    "metadata": {
      "topics": [
        "氷の収納量と製氷時間",
        "製氷操作方法（急速製氷・製氷停止）",
        "製氷に関する注意事項",
        "製氷トラブルと対処法",
        "操作パネル表示例"
      ],
      "keywords": [
        "R-HWS47X",
        "R-HWS47XL",
        "製氷時間",
        "急速製氷",
        "製氷停止",
        "製氷ケース",
        "冷凍室温度設定",
        "節電モード",
        "検知レバー",
        "操作パネル"
      ],
      "section_header": "製氷",
      "page_type": "instruction"
    }
  },
  {
    "page": 16,
    "summary": "このページでは冷凍室の構造と収納方法について説明しています。冷凍室は上段と下段に分かれ、食品の種類や大きさに応じて適切なケースに収納することが推奨されています。また、安全に使用するための注意点も記載されています。",
    "content": "```markdown\n# 冷凍室\n\n3段ケースでたっぷりすっきりおいしく冷凍します。\n\n| 冷凍室上段                                 | 冷凍室下段                                         |\n|--------------------------------------------|---------------------------------------------------|\n| 日常使う食品や、使いかけの食品を保存する際に、ご使用ください。 | 3段ケースでたっぷり収納できて、スッキリ整理ができます。 長く保存する食品や、溶けやすいアイスクリームなどの収納に適しています。 |\n\n- 冷凍室上段  \n  - 上段フリーザーケース  \n  - ハンドル\n\n- 冷凍室下段  \n  - 薄物ケース（急冷凍スペース）  \n    ※アルミトレイ付き  \n  - 小物ケース  \n  - 大物ケース  \n  - たて収納スペース  \n  - ハンドル\n\n> ### ご注意\n> - 薄物ケースおよび小物ケースは、ハンドルを持って操作してください。  \n> 指をはさみ、けがの原因になります。\n\n---\n\n## 収納食品\n\n| 場所         | 用途                                                         |\n|--------------|--------------------------------------------------------------|\n| 冷凍室上段   | フリージングパック、密閉容器、食パンなど                     |\n| 冷凍室下段   | 薄物ケース：小物冷凍食品など                                  |\n|              | 急冷凍スペース：肉・魚やごはんをすばやく冷凍するとき       |\n|              | 小物ケース：フリージングパック、密閉容器など                 |\n|              | 大物ケース：冷凍食品、アイスクリームなど                     |\n|              | たて収納スペース：冷凍専用ペットボトルなど                   |\n\n- 温かい食品を保存するときは、**手で持てるくらいの温度（50℃以下）に冷ましてから入れてください。**\n\n---\n\n## 食品を収納するとき\n\n食品の種類や大きさに合わせて収納します。収納する食品の高さは各ケースの端面を目安にしてください。  \n食品が上のケースやしきりに触れないように収納します。\n\nドアが確実に閉まらなくなり、冷えが悪くなることがあります。また、食品や各ケースが破損することがあります。\n\n> ### ご注意\n> - 薄物ケースにペットボトルを入れないでください。  \n> ペットボトルが凍ると膨張して取り出せなくなります。  \n> - 薄物ケースおよび小物ケースを取りはずしたまま使用しないでください。  \n> ケース奥側に食品が落ちて、ドアが閉まらなくなることがあります。  \n> - 冷凍対応ペットボトルなど、凍らせてもよい食品のみ収納してください。\n\n---\n\n[図: 冷凍室上段・下段のドアのしきりと各ケース端面の説明]\n\n- 冷凍室上段ドア、冷凍室下段ドアのしきり位置\n- ケース端面  \n- 上段フリーザーケース  \n- 薄物ケース、小物ケース、大物ケースの位置\n```\n",
    "metadata": {
      "topics": [
        "冷凍室の構造",
        "各ケースの用途",
        "食品の収納方法",
        "安全上の注意点",
        "保管食品の種類"
      ],
      "keywords": [
        "冷凍室",
        "上段フリーザーケース",
        "薄物ケース",
        "小物ケース",
        "大物ケース",
        "急冷凍スペース",
        "ハンドル",
        "冷凍食品",
        "アイスクリーム",
        "ペットボトル"
      ],
      "section_header": "冷凍室",
      "page_type": "instruction"
    }
  },
  {
    "page": 17,
    "summary": "このページは、食品を迅速に冷凍するための「急冷凍」機能の使い方と注意点を説明しています。また、冷凍室の温度調節方法についても解説し、標準設定からの変更や消費電力量の違いについて触れています。食品はラップで包みアルミトレイに密着させることが効率的な冷凍のポイントです。",
    "content": "```markdown\n# 食品を急いで凍らせる（「急冷凍」を使う）\n\nアルミトレイの効果とあわせて、よりすばやく食品を冷凍します。\n\n食品をラップやフリージングパックにつつんでアルミトレイの上に置いてください。  \n食品を薄く小分けにすると、中心まで すばやく凍るだけでなく、取り出しやすくて便利です。  \n温かい食品を保存するときは、**手で持てるくらいの温度（50℃以下）に冷ましてから入れてください。**\n\n急冷凍スペース\n\n---\n\n## 設定するとき\n\n「冷却モード」を押して「急冷凍」ランプを点灯させる\n\n約90分で運転を自動終了し、「急冷凍」ランプが消灯します。\n\n---\n\n## 途中で解除するとき\n\n「冷却モード」を押してランプを消灯させる\n\n### お知らせ\n- 「クイック冷却」と「急冷凍」は同時には設定できません。  \n- 「急冷凍」運転時は冷凍室を優先して冷却しますので、冷蔵室のドア開閉が多いときなど冷蔵室の温度が上がりやすくなります。  \n- 「急冷凍」運転終了後60分以内に、再び「急冷凍」を設定すると、「急冷凍」ランプは点灯しますが、「急冷凍」運転は約60分経過してから運転を行います。冷蔵室の温度が上がることを防ぐためです。  \n- 食品は積み重ねずにアルミトレイに密着させるように置くと、より効率よく冷凍することができます。  \n- 食品がアルミトレイにはりつくことを防ぐため、必ずラップやフリージングパックでつつんでください。  \n- 「急冷凍」運転中は通常よりも消費電力量が多くなります。  \n\n---\n\n# 温度の調節（冷凍室）\n\n「冷凍」を押して温度の変更する\n\nご購入時は、「標準」に設定されています。通常は「標準」の設定でお使いください。  \n夏場などに、冷えが悪いと感じるときは、「強め」でお使いください。\n\n### お願い\n冷えすぎると感じるときは、「標準」または「弱め」でご使用ください。\n\n### お知らせ\n- 庫内の温度は使用条件により多少変動します。  \n- 温度をさらに細かく調節することもできます。→(P.20)  \n- 冷凍室「強め」は「標準」設定に比べ、消費電力量が多くなります。  \n- 冷凍室の温度設定を変更すると、製氷室の温度も変わります。\n\n---\n\n冷凍室温度の目安  \n「強め」は「標準」より約2～4℃低め  \n「弱め」は「標準」より約2～4℃高め\n\n---\n\n■操作パネルイメージ\n\n- 強め  \n- 標準（●）  \n- 弱め  \n\n冷凍\n```\n",
    "metadata": {
      "topics": [
        "急冷凍機能の使い方",
        "食品の冷凍効率向上方法",
        "冷凍室の温度調節",
        "消費電力量の注意点",
        "操作パネルの説明"
      ],
      "keywords": [
        "急冷凍",
        "アルミトレイ",
        "冷凍室",
        "冷却モード",
        "ラップ",
        "フリージングパック",
        "50℃以下",
        "温度設定",
        "強め",
        "標準",
        "弱め"
      ],
      "section_header": "冷凍機能の操作",
      "page_type": "instruction"
    }
  },
  {
    "page": 18,
    "summary": "このページは野菜室の構造や機能、食品の適切な収納方法について説明しています。プラチナ触媒やうるおいユニットにより野菜の鮮度を保ち、上段・下段・たて収納スペースに合わせて適切な野菜や果物を収納する注意点も記載されています。",
    "content": "```markdown\n# 野菜室\n\n新鮮スリープ野菜室では、プラチナ触媒で炭酸ガスの濃度を高めて野菜の呼吸活動を抑え、眠らせるように、またうるおいユニットで適度な水分を維持して野菜を保存します。\n\n---\n\n### 野菜室の構造\n\n- **プラチナ触媒**  \n  食品のニオイ成分や野菜のエチレンガスを分解し炭酸ガスに変えることで、食品の鮮度低下を抑えます。  \n  プラチナ触媒は交換の必要がありません。取りはずさないでください。\n\n- **上段ケース**  \n- **ハンドル**  \n- **しきり**  \n- **下段ケース**  \n  ※取りはずす場合は、しきりを取りはずしてから下段ケースを取りはずしてください。  \n  しきりが落下するおそれがあります。\n\n- **うるおいユニット**  \n  ※取りはずさないでください。\n\n- **たて収納スペース**\n\n---\n\n### ご注意\n- 上段ケースは、ハンドルを持って操作してください。  \n  指をはさみ、けがの原因になります。\n\n---\n\n## 収納食品\n\n| スペース        | 内容                                   | 例                                                          |\n|-----------------|--------------------------------------|-------------------------------------------------------------|\n| 上段スペース    | 使いかけの野菜や小物野菜、果物など   | トマト、ピーマン、イチゴ、グレープフルーツ                 |\n| 下段スペース    | 葉物野菜や大物野菜など                | ホウレンソウ、小松菜、チンゲン菜、ブロッコリー、キャベツ、レタス |\n| たて収納スペース | 背の高い野菜（きゅうり、アスパラガスなど）、2Lペットボトルなど |                                                             |\n\n---\n\n## 食品を収納するとき\n\n食品の種類や大きさに合わせて収納します。\n\n- **収納する食品の高さに注意してください。**  \n  - ドアが確実に閉まらなくなり、冷えが悪くなることがあります。また、食品や各ケースが破損することがあります。  \n  - 食品やペットボトルの種類により収納できない場合があります。\n\n- **上段ケースを取りはずしたまま使用しないでください。**  \n  - ケース奥側に食品が落ちて、ドアが閉まらなくなることがあります。\n\n- **無理に食品、飲料などを押し込まないでください。**  \n  - しきりや各ケースが破損することがあります。\n\n---\n\n### 高さの目安\n\n- 下段スペースの食品の高さ  \n  ![図: 野菜室ドアと下段スペースに収納された食品の高さのイメージ]()\n\n- たて収納スペースの食品の高さ  \n  ![図: 野菜室ドアとたて収納スペースに収納された食品の高さのイメージ]()\n\n- 上段スペースの食品の高さ  \n  ![図: 野菜室ドアと上段スペースに収納された食品の高さのイメージ]()\n\n---\n```\n",
    "metadata": {
      "topics": [
        "プラチナ触媒の働き",
        "野菜室の構造",
        "食品の収納方法",
        "収納スペースの用途",
        "高さの目安と注意事項"
      ],
      "keywords": [
        "野菜室",
        "プラチナ触媒",
        "炭酸ガス",
        "うるおいユニット",
        "上段ケース",
        "下段ケース",
        "たて収納スペース",
        "食品の高さ",
        "収納注意",
        "呼吸活動抑制"
      ],
      "section_header": "冷蔵庫の収納機能",
      "page_type": "instruction"
    }
  },
  {
    "page": 19,
    "summary": "このページは、野菜ごとの適切な保存方法や常温保存に適した野菜、低温障害を起こしやすい食品について解説しています。また、野菜室での湿度管理や結露対策、乾燥食品の保存方法についての注意点も紹介しています。",
    "content": "```markdown\n# 野菜を保存するときのコツ\n\n| 種類               | 保存するときのコツ                             | 種類             | 保存するときのコツ                                      |\n|--------------------|----------------------------------------------|------------------|-------------------------------------------------------|\n| キャベツ レタス    | 芯をくり抜き、ぬらしたペーパータオルを詰めて保存。 | ホウレンソウ 小松菜 チンゲン菜 | 傷んだ葉を取り除いて、立てて保存。                      |\n| 大根 にんじん      | 葉がついている場合は葉を落として保存。         | アスパラガス     | 立てて保存。                                           |\n| ブロッコリー       | ビニール袋に入れて保存。                       | しいたけ         | 傘を下にして保存。(水気が多い場合は紙袋に入れて保存) |\n| かぼちゃ（カット） | 種の部分を取り除いて保存。                     | しょうが         | 水気をよくふき取って保存。                             |\n| きゅうり           | 水気をよくふき取って立てて保存。               |                  |                                                       |\n\n---\n\n## 常温保存がおすすめの野菜\n- にんにく、玉ねぎ、じゃがいも、さつまいも、かぼちゃ（丸ごと）は冷暗所（室内温度が一定で低めに保たれ、直射日光が当たらない場所）に保存することをおすすめします。\n\n---\n\n## 低温障害を起こしやすい食品\n長期間野菜室に入れると食品によって、色が変わったり、味が落ちたりします。また、ビタミンCが減ったり、カビが生えたり、腐りはじめたりすることもあります。\n\n- 野菜  \n  トマト、ピーマン、きゅうり、なす、さやいんげん、さつまいも、おくら など\n- 果物  \n  バナナ、パイナップル、マンゴー、パパイヤ、アボカド、レモン など\n\n食べる前に短時間冷蔵庫で冷やすとおいしく食べられます。\n\n---\n\n## こんなときは\n- 野菜が少ないときは、高い湿度を保てないことがありますので、ラップをして保存してください。\n- 野菜室は湿度が高いため、野菜の量や種類によっては、ケースやうるおいユニット表面、食品表面などに結露することがあります。結露が気になる場合は、食品にラップをしてください。\n- 食品の袋や容器によってうるおいユニットがふさがれた場合、結露が多く発生します。うるおいユニット部分をふさいでいる食品の袋や容器を他の所に移動してください。\n- ケースに水がたまると食品が傷みやすくなるので、やわらかい布でふき取ってください。\n- 米、海苔などの乾燥食品を野菜室に収納する際は、密閉した容器（袋）に入れてから収納してください。乾燥食品が吸湿することがあります。\n\n---\n\n## お知らせ\nたて収納スペースは他のスペースに比べ、温度が少し高めになります。\n```",
    "metadata": {
      "topics": [
        "野菜の保存方法",
        "常温保存の推奨野菜",
        "低温障害の注意点",
        "野菜室の湿度・結露対策",
        "収納時の注意事項"
      ],
      "keywords": [
        "キャベツ",
        "レタス",
        "ホウレンソウ",
        "アスパラガス",
        "低温障害",
        "結露",
        "冷暗所保存",
        "ラップ保存",
        "うるおいユニット",
        "乾燥食品"
      ],
      "section_header": "野菜の保存方法",
      "page_type": "instruction"
    }
  },
  {
    "page": 20,
    "summary": "このページでは冷蔵室と冷凍室の温度を11段階で微調節する方法を説明しています。操作方法やランプの表示パターン、操作パネルの機能、そして元の3段階調節に戻す解除方法についても解説しています。",
    "content": "```markdown\n# いろいろな機能\n\n## 温度微調節（冷蔵室・冷凍室）\n\n冷蔵室と冷凍室の温度設定をさらに細かく１１段階に調節することができます。\n\n1. 冷蔵室ドアと冷凍室下段ドアを開ける  \n2. 「冷蔵」をピーッと鳴るまで５秒以上押しつづける  \n3. 冷凍室下段ドアを閉める  \n4. 「冷蔵」または「冷凍」を押して各室を調節する  \n押すごとに下図のようにランプが順番に切り替わります。\n\n### 冷蔵（■標準：点灯、■準標準：点滅、□標準：消灯）\n\n| ランプ  | チルド   | チルド   | チルド   | チルド   | チルド   | チルド   | チルド   | チルド   | チルド   | チルド   | チルド   | チルド   |\n|---------|----------|----------|----------|----------|----------|----------|----------|----------|----------|----------|----------|----------|\n|         | □標準   | ■標準    | ■標準    | ■標準    | ■標準    | ■標準    | ■標準    | ■標準    | ■標準    | ■標準    | ■標準    | □標準   |\n|         | □弱め   | □弱め    | □弱め    | □弱め    | □弱め    | □弱め    | □弱め    | □弱め    | □弱め    | □弱め    | □弱め    | □弱め   |\n| 設定    | さらに弱め | 弱め     | →        | →        | →        | 標準     | →        | →        | →        | チルド   | さらに強め |\n\n### 冷凍（■標準：点灯、■準標準：点滅、□標準：消灯）\n\n| ランプ  | ■強め   | ■強め   | ■強め   | ■強め   | ■強め   | ■強め   | ■強め   | ■強め   | ■強め   | ■強め   | ■強め   | ■強め   |\n|---------|---------|---------|---------|---------|---------|---------|---------|---------|---------|---------|---------|---------|\n|         | □標準  | □標準  | ■標準  | ■標準  | ■標準  | ■標準  | ■標準  | ■標準  | ■標準  | ■標準  | ■標準  | □標準  |\n|         | ■弱め  | ■弱め  | ■弱め  | ■弱め  | ■弱め  | ■弱め  | ■弱め  | ■弱め  | ■弱め  | ■弱め  | ■弱め  | □弱め  |\n| 設定    | さらに弱め | 弱め   | →       | →       | →       | 標準    | →       | →       | →       | 強め    | さらに強め |\n\n---\n\n### 操作パネル\n\n- 急速製氷  \n- 製氷  \n- 製氷停止  \n- 急冷凍  \n- クイック冷却  \n- 製氷  \n- 冷却モード  \n\n- 強め  \n- 標準  \n- 弱め  \n- 節電  \n\n- チルド  \n- 標準  \n- 弱め  \n\n- 冷凍  \n- 冷蔵  \n\n（5秒以上押す）\n\n---\n\n## 解除\n\n手順1、2、3の操作をする  \n操作音がピピッと鳴り、通常の調節（3段階）に戻ります。\n```\n",
    "metadata": {
      "topics": [
        "温度微調節",
        "冷蔵室と冷凍室の設定",
        "操作パネルの機能",
        "温度設定解除"
      ],
      "keywords": [
        "温度微調節",
        "冷蔵室",
        "冷凍室",
        "11段階設定",
        "操作パネル",
        "急速製氷",
        "急冷凍",
        "クイック冷却",
        "節電",
        "チルド"
      ],
      "section_header": "いろいろな機能",
      "page_type": "instruction"
    }
  },
  {
    "page": 21,
    "summary": "このページでは、ドアアラーム機能の動作時間と音の種類、及び操作パネルのランプの挙動について説明しています。また、ドアアラームと操作音の音量調整方法や注意点が記載されており、冷蔵室内のトリプルパワー脱臭機能についても紹介されています。",
    "content": "```markdown\n# ドアアラーム\n\nドアのいずれかを1分以上開放すると、音でドアが開いていることをお知らせします。  \nドアアラーム機能は、冷蔵室、製氷室、冷凍室下段についています。（冷凍室上段、野菜室にはついていません）\n\n| ドアの開放時間                        | 30秒後（「節電モード」設定時） | 1分後      | 2分後      | 3分以降                    |\n|-------------------------------------|------------------------------|------------|------------|-------------------------|\n| アラーム音                           | ピーッ（3回）                 | ピーッ（3回） | ピーッ（5回） | ピーッ（連続）音量大きめ     |\n| 操作パネルのランプ                   | —                            | —          | —          | 点滅                      |\n\n> #### お知らせ  \n> 操作パネルのランプが点滅中はボタンを押しても反応しません。一度ドアを閉めてから操作してください。\n\n---\n\n# ドアアラームと操作音の音量調整\n\nドアアラームと操作音の音を大きめにしたり、音を鳴らないように設定することができます。  \nご購入時は「標準」に設定されています。\n\n**冷蔵** を設定音が鳴るまで3秒以上押しつづける\n\n操作音の音量が「標準」▶「大きめ」▶「切」に切り替わります。設定の切り替えを繰り返し、ご希望の音量（下表参照）に切り替えてください。\n\n| 音量   | 標準 | 大きめ    | 切     | 標準      |\n|--------|------|---------|--------|----------|\n| 設定音 | —    | ピーピッ | ピーッ | ピピッ  |\n\n（ご購入時）\n\n> #### お知らせ\n> - ドアアラームと操作音の片方のみを音量調整することはできません。  \n> - 音量を「切」に設定すると、ドアが3分以上開いている場合でも、ドアが開いていることをお知らせする操作パネルのランプ点滅はしません。  \n> - 音量を「切」に設定した場合でも、「製氷おそうじ」のアラームは鳴ります。→（P.25）  \n> また、3秒以上押しつづける操作をした場合、操作完了後に設定音が鳴ります。  \n> - 電源プラグを抜き差ししたり、停電復帰した後は「標準」設定に戻ります。\n\n---\n\n# トリプルパワー脱臭（冷蔵室）\n\n3種類の脱臭素材の組み合わせによって、硫黄系・チッ素系・アルデヒド系・酸系の4大臭気をふくむ庫内のさまざまなにおいを脱臭します。\n```",
    "metadata": {
      "topics": [
        "ドアアラームの動作",
        "アラーム音の種類とタイミング",
        "操作音の音量調整",
        "音量設定の注意点",
        "トリプルパワー脱臭機能"
      ],
      "keywords": [
        "ドアアラーム",
        "冷蔵室",
        "製氷室",
        "冷凍室下段",
        "アラーム音",
        "操作音",
        "音量調整",
        "節電モード",
        "トリプルパワー脱臭",
        "臭気"
      ],
      "section_header": "便利機能",
      "page_type": "instruction"
    }
  },
  {
    "page": 22,
    "summary": "このページは、冷蔵庫の節電モードについて説明しています。節電モードを設定すると冷却が弱まり消費電力が抑えられるが、冷凍や製氷時間が長くなる場合があります。また、急速製氷や急凍結などのモードを使用すると節電は一時解除されます。",
    "content": "```markdown\n# 節電する\n\n## 節電モード\n\n「節電モード」に設定すると、各室の冷却を弱める運転に切り替わるため、節電ができます。  \n冷蔵室ドアを30秒以上開放すると、ドアアラームが鳴り冷蔵室のLED庫内灯が減光して、ドアを開けている時間を短くするようお知らせします。また、長い時間ドアの開閉がない場合は、庫内をゆっくり冷やすことで、さらに消費電力量を抑えます。\n\n---\n\n## 設定するとき\n\nご購入時は、「切」（消灯）に設定されています。  \n[節電] を押して「節電」ランプを点灯させる\n\n### ■操作パネル\n\n| ご購入時 | 設定時 |\n| -------- | -------- |\n| [節電]（押す） | [節電]（点灯） |\n\n---\n\n## 解除するとき\n\n[節電] を押して「節電」ランプを消灯させる\n\n---\n\n## お知らせ\n\n- 冷却を弱める運転をするため、アイスクリームがやわらかくなるなど、冷えが弱いと感じられる場合があります。また、食品を冷凍させる場合の凍結時間や、製氷時間は通常より長くなります。\n- 「節電モード」設定中に「急速製氷」「急冷凍」「クイック冷却」を設定した場合には冷却を弱める運転を一時解除します。\n- 「節電モード」設定中に、冷凍室、冷蔵室の両方またはいずれかの温度設定を「弱め」でご使用の場合、「弱め」設定の各室については食品の鮮度保持のため、さらに冷却を弱める運転は行いません。\n```\n",
    "metadata": {
      "topics": [
        "節電モードの概要",
        "節電モードの設定方法",
        "節電モードの解除方法",
        "節電モード中の動作特性",
        "節電モードの注意点"
      ],
      "keywords": [
        "節電モード",
        "冷却弱め",
        "ドアアラーム",
        "LED庫内灯",
        "冷蔵室ドア",
        "急速製氷",
        "急冷凍",
        "クイック冷却",
        "凍結時間",
        "冷却時間"
      ],
      "section_header": "節電する",
      "page_type": "instruction"
    }
  },
  {
    "page": 23,
    "summary": "このページでは冷蔵庫のお手入れ方法について詳しく説明しています。電源プラグを抜く安全対策の重要性や、各部の掃除頻度と具体的な手入れ方法、使用禁止の洗剤や道具、注意事項が記載されています。定期的な掃除により製品の性能維持と長持ちを促進します。",
    "content": "```markdown\n# お手入れ\n\n⚠️ 警告  \nお手入れの際には、必ず電源プラグをコンセントから抜く\n\n---\n\n## ■汚れに気づいたら  \nすぐにふき取りましょう。見えない部分も年に一回はお手入れすることをおすすめします。\n\n| 項目 | 内容 | 頻度 |\n|-------|-------|-------|\n| 電源プラグ | 電源プラグをコンセントから抜き、乾いた布でホコリなどをふき取る  \n火災や感電を防ぐために →(P.4) | 年に1、2回 |\n| ドアパッキング | やわらかい布にぬるま湯をふくませて汚れをふき取る  \n汚れやすいところなので、汚れをよくふき取ってください。 | 月に1回 |\n| ドア表面 | やわらかい布にぬるま湯をふくませて汚れをふき落とし、その後、乾いた布できれいにふき取る  \n表面にテープのりなどが残っているときは、プラスチック消しゴムでこすってから乾いた布でふくと取り除くことができます。 | 月に1回 |\n| 各棚ポケット | やわらかい布にぬるま湯をふくませて汚れをふき取る  \n取りはずしかたは →(P.26) | 3か月に1回 |\n| 汁受け部 | やわらかい布にぬるま湯をふくませて汚れをふき取る  \n汁がたまったり汚れた場合、ふき取ってください。 | 月に1回 |\n| 冷蔵庫背面・側面・床 | 脚カバーを取りはずし、調節脚を床から浮かせ、冷蔵庫を手前に引き出し、汚れをふき取る  \n- 背面や側面下部のプラスチック部品周辺は空気の対流により、細かいホコリが付着して汚れやすいところです。  \n- 傷のつきやすい床では、保護用の板などを敷いてください。  \n- 振動音が気になるときや、湿気による背面壁の変色、汚れが気になるときは背面壁から離して（2cm以上）設置してください。 | 年に1、2回 |\n| ケース | やわらかい布にぬるま湯をふくませて汚れをふき取る  \n野菜室の下段ケースを水洗いした場合は、ひっくり返して水を抜いた後、十分に水分をふき取ってください。また、歯ブラシやたわしなど毛足の長いものは使わないでください。ケースの傷つきや、うるおいユニットの破損の原因になります。  \n取りはずしかたは →(P.27)  \n※プラチナ触媒は水洗いしないでください。 | 3か月に1回 |\n\n---\n\n## お願い  \n●ドア、塗装面やプラスチック、ガラス面を傷めたり、変色させたりする場合がありますので、次のものは使わないでください。\n\n| × | × | × | × | × | × | × | × |\n|---|---|---|---|---|---|---|---|\n| アルカリ性、弱アルカリ性の台所用洗剤、ガラス用洗剤、塩素系漂白剤 | たわし、研磨スポンジ、化学ぞうきん | みがき粉、粉せっけん | ベンジン、シンナー、アルコール | 熱湯 |\n\n- 洗剤の「家庭用品品質表示法に基づく表示」の「液性」の欄をご確認ください。  \n- 食用油、かんきつ類の果汁、食品の汁がついたときは、必ずふき取ってください。付着した製品が変色したり割れたりする場合があります。  \n- ケース類や引き出しレールの可動接触面には潤滑剤が塗られているのでふき取らないでください。（潤滑剤は食品衛生法に適合しています）  \n- マグネットや吸盤を本体側面やドア表面に付けた場合、跡が残る場合があります。  \n- 電源プラグを抜いた場合、操作パネルの設定が解除されることがありますので、お好みに合わせて再設定してください。  \n- 給水タンクや小物ケースなど樹脂製の部品は、食器洗い乾燥機や熱湯などで洗わないでください。（部品が変形するおそれ）  \n- 汚れが落ちにくいときは、台所用洗剤（中性）をぬるま湯で薄めて使い、水拭きをしてください。\n\n---\n23\n```",
    "metadata": {
      "topics": [
        "安全な電源プラグの取り扱い",
        "各部位の清掃手順と頻度",
        "使用禁止の洗剤・器具",
        "注意事項とメンテナンスのポイント"
      ],
      "keywords": [
        "電源プラグ",
        "ドアパッキング",
        "冷蔵庫背面",
        "乾いた布",
        "ぬるま湯",
        "プラスチック消しゴム",
        "台所用洗剤中性",
        "潤滑剤",
        "プラチナ触媒",
        "掃除頻度"
      ],
      "section_header": "お手入れ",
      "page_type": "maintenance"
    }
  },
  {
    "page": 24,
    "summary": "このページでは、特鮮氷温ルームの月に1回の清掃方法と、給水タンクの週に1回の手入れ手順を詳述しています。各部品の取り外しや洗浄方法、浄水フィルターの取り扱い注意点、そして給水タンクの組み立て方が説明されています。さらに、長期間自動製氷機を使用しない場合の給水タンクの乾燥と保管についての注意も記載されています。",
    "content": "```markdown\n# お手入れ ～つづき～\n\n## 特鮮氷温ルーム　月に1回\n\n### 1 特鮮氷温ケースを引き出す\n取りはずしかたは →(P.26)  \n特鮮氷温ケース内に収納されている食品は必ず取り出してください。\n\n### 2 下記部品を、やわらかい布にぬるま湯をふくませてふく\n※洗剤などは使わないでください。\n\n（図：容器部分を布で拭いている様子）\n\n### 3 特鮮氷温ケースを取り付ける  \n取り付けかたは →(P.26)\n\n---\n\n## 給水タンク　週に1回\n\n### 1 給水タンクを取り出し、ふたを取りはずす\n1. ふたを矢印の方向へ傾ける。  \n2. ふたの前側を持ち上げる。\n\n（図：ふたを外す動作のイラスト）\n\n### 2 ふたからパッキンとケースを取りはずす  \nケースは引っ張ってふたから取りはずします。\n\n### 3 ケースから浄水フィルターを取りはずす  \n浄水フィルターのつまみを指で引っぱってつめからはずしケースを取りはずします。\n\n（図：つまみをつまんで浄水フィルターを外す動作）\n\n### 4 給水タンクの各部品を水洗いする  \nやわらかいスポンジで水洗いしてください。  \n洗剤などは使わないでください。  \n※浄水フィルターのフィルター部分は、スポンジを使わないでください。やさしく水で流してください。\n\n（図：フィルター部分のイラスト）\n\n#### お知らせ\n- 浄水フィルター交換の目安は約3～4年です。 →(P.35)\n\n### 5 給水タンクの各部品を取り付けてから、水を入れてセットする  \nふたとケースは凹部を合わせ差し込んでください。\n\n（図：ふたの凹部を合わせて差し込む様子）\n\nふたの後側から差し込み、矢印の方向へ閉めてください。\n\n（図：ふたの閉め方）\n\n× パッキンがねじれてしまっている。  \n× ふたがしっかりと閉まっておらず浮いている。\n\n---\n\n#### お願い\n自動製氷機を長期間使わないときは、給水タンクのお手入れ後に、給水タンクをよく乾かして所定の位置にセットしてください。  \n（特に浄水フィルターはよく乾かしてください）\n\n---\n```",
    "metadata": {
      "topics": [
        "特鮮氷温ルームの清掃",
        "給水タンクの分解と洗浄",
        "浄水フィルターの取り扱いと交換目安",
        "部品の取り外し・取り付け方法",
        "長期間使用しない際の給水タンクの対応"
      ],
      "keywords": [
        "特鮮氷温ケース",
        "給水タンク",
        "浄水フィルター",
        "お手入れ",
        "分解",
        "月に1回",
        "週に1回",
        "水洗い",
        "パッキン",
        "交換目安3～4年"
      ],
      "section_header": "お手入れ",
      "page_type": "maintenance"
    }
  },
  {
    "page": 25,
    "summary": "このページでは、自動製氷機を初めて使う場合や1週間以上使用しなかった場合の製氷おそうじ手順を説明しています。操作方法は製氷おそうじボタンを5秒以上押し、約4分間ランプ点滅とアラームを確認して行い、その後製氷ケースの水を拭き取ることで終了します。安全のため、製氷機の機械部には手を入れず、ドアの開閉を控える注意点も記載されています。",
    "content": "```markdown\n# 製氷おそうじ　はじめてお使いのとき　自動製氷機を１週間以上使わなかったとき\n\n---\n\n⚠️ **警告**  \n自動製氷機の機械部には手を入れない  \n（けがをするおそれ）\n\n---\n\n製氷皿や水の通り道を水洗いします。  \n操作の前に、次のことをご確認ください。\n\n## 準備\n\n- **給水タンク**  \n  ・満水線まで水が入っている。  \n  ・「タンクセット位置」の線を越えて正しくセットされている。\n\n- **製氷ケース**  \n  ・氷が残っている場合は取り除いてください。\n\n確認したら、冷蔵室以外のドアを閉めて、次の操作をしてください。\n\n---\n\n## 1. 製氷をアラームが鳴り出すまで5秒以上押しつづける\n\n「急速製氷」「製氷」「製氷停止」の3つのランプが同時に点滅し、「製氷おそうじ」がスタートします。（約4分間）\n\n- 冷蔵室のドアを閉めてください。  \n- 約4分間ランプが点滅し、アラームが鳴りつづけます。  \n- 「製氷おそうじ」は、途中で中止することはできません。  \n- 「製氷おそうじ」中に冷蔵庫のいずれかのドアを開けると、正常に動作しない場合があります。  \n  終了するまで全てのドアの開閉を行わないでください。  \n- ドアアラームを鳴らないように設定しているときでもアラームは鳴ります。→(P.21)\n\n---\n\n## 2. アラームが終わったら、製氷ケースの奥にある切りかき部分をふさぐようにして製氷ケースの底にきれいなタオルなどを敷く\n\n「製氷おそうじ」のときにたまった水が、製氷ケース奥の切りかき部分からこぼれるのを防ぐため、吸水用のタオルを敷きます。\n\n---\n\n## 3. 製氷ケースを取りはずし、ケース内の水をきれいにふき取ったあと製氷室にセットする\n\n水分をふき取ったタオルなどは取り除いてください。  \n給水タンクに残った水は、そのまま製氷にお使いいただけます。  \n「製氷おそうじ」終了後は、「製氷」に設定されます。\n\n---\n\n[図: 給水タンクと製氷ケースの位置、製氷おそうじの操作パネルの説明、製氷ケースの切りかき部分とタオルの配置]\n```\n",
    "metadata": {
      "topics": [
        "自動製氷機の清掃",
        "製氷おそうじ機能の操作方法",
        "製氷機の準備と注意点",
        "給水タンクと製氷ケースの取り扱い",
        "アラーム操作と安全注意事項"
      ],
      "keywords": [
        "自動製氷機",
        "製氷おそうじ",
        "給水タンク",
        "製氷ケース",
        "アラーム",
        "タオル",
        "急速製氷",
        "製氷停止",
        "清掃手順",
        "安全警告"
      ],
      "section_header": "製氷おそうじ",
      "page_type": "instruction"
    }
  },
  {
    "page": 26,
    "summary": "このページは冷蔵庫の各部品の取りはずし方と取り付け方について説明しています。各棚やドアポケット、特鮮氷温ケースの具体的な操作手順と注意点が記載されており、安全かつ正しく作業を行うための指示が示されています。特に部品を取り外す際の注意や破損防止、けがの防止について強調しています。",
    "content": "```markdown\n# 部品の取りはずしかた・取り付けかた\n\n> ### ご注意\n> - 部品を取りはずすときは、部品に載っている食品を取り除いてから行ってください。\n> - ここで説明している部品以外は、取りはずさないでください。  \n>   説明していない部品を取りはずして掃除をしたいときなどは、修理に関するご相談窓口にご相談ください。→(P.35)\n> - 野菜室のプラチナ触媒は取りはずさないでください。また、水洗いしないでください。\n\n---\n\n## A 高さかわるん棚 上段・中段\n\n### お願い\n- 棚を取りはずす際は、まず上にある棚を取りはずしてから、下にある棚を取りはずしてください。  \n- 棚を取り付けの際は、下に取り付ける棚から取り付けてください。\n\n1. 棚の奥を少し持ち上げ、手前に引き出す  \n   上段・中段\n\n2. 図のように棚を立てる\n\n3. 回転させて取りはずす\n\n> ### ご注意\n> ガラス棚は重いため取り付け、取りはずしには十分注意してください。落下すると打撲や破損によりけがをするおそれがあります。\n\n---\n\n## B 高さかわるん棚 下段\n\n- 全体を少し持ち上げて取りはずす  \n  （図：固定棚と高さかわるん棚下段）\n\n---\n\n## C 固定棚\n\n- 高さかわるん棚下段を取りはずした後、棚しきりを押さえながら、棚の奥を少し持ち上げ、手前に引き出す\n\n---\n\n## D 棚しきり\n\n1. 奥を持って手前に回転させる  \n2. 奥側に押しながら取りはずす\n\n---\n\n## E ドアポケット\n\n- 底面の左右を軽くたたきながら持ち上げて取りはずす  \n  （固めに固定してあります）\n\n> ### ご注意\n> - 取り付けの際は、最後までしっかり入れてください。  \n> - 取り付けが不十分だとはずれて落下し、けがの原因になります。\n\n---\n\n## F 特鮮氷温ケース\n\n### 取りはずしかた\n- 特鮮氷温ケースを引き出し、手前を軽く持ち上げて斜め上に引き出す\n\n> ### ご注意\n> - 特鮮氷温ケースを持つときは点線から奥を持ってください。  \n> （指をドアではさむおそれ）\n\n> ### ご注意\n> - 特鮮氷温ケースを取りはずした際は、ドアやハンドルだけを持つのではなく、ケース全体を持ってください。  \n> （部品の破損につながるおそれ）\n\n### 取り付けかた\n- 特鮮氷温ケースの左右の突起を容器のガイドレールの下に滑らせるように入れる\n\n### お願い\n- 取り付けた後に何度か出し入れして、正しく取り付けたことを確認してください。\n\n---\n\n## 図の部品表記\n\n- A: 高さかわるん棚 上段・中段\n- B: 高さかわるん棚 下段\n- C: 固定棚\n- D: 棚しきり\n- E: ドアポケット\n- F: 特鮮氷温ケース\n- G: （記載なし）\n- H: （記載なし）\n- I: （記載なし）\n\n---\n\n26\n```",
    "metadata": {
      "topics": [
        "部品の取りはずし方法",
        "部品の取り付け方法",
        "安全上の注意点",
        "各棚の構造と扱い方",
        "特鮮氷温ケースの取り扱い"
      ],
      "keywords": [
        "高さかわるん棚",
        "固定棚",
        "棚しきり",
        "ドアポケット",
        "特鮮氷温ケース",
        "プラチナ触媒",
        "取りはずし",
        "取り付け",
        "注意事項",
        "冷蔵庫部品"
      ],
      "section_header": "部品の取りはずしかた・取り付けかた",
      "page_type": "instruction"
    }
  },
  {
    "page": 27,
    "summary": "このページでは、製氷ケース、冷凍室の薄物・小物・大物ケース、野菜室の上段・下段ケースやしきりの取り外し・取り付け方法を詳しく説明しています。正しい取り付け方法や注意点、開閉時の異音や半ドア防止についても解説されています。",
    "content": "```markdown\n## G 製氷ケース（製氷室）・上段フリーザーケース（冷凍室上段）\n\n### ドアを開け、ケースを手前に持ち上げる  \n取り付けの際は、ケース底面を枠に載せてセットしてください。\n\n![イラスト: 製氷ケースの取り外し](ケース底面、枠)\n\n---\n\n## H 薄物ケース・小物ケース・大物ケース（冷凍室下段）\n\n### 1 ドアを開け、薄物ケース・小物ケースをそれぞれ引き出す  \n- 薄物ケース  \n- 小物ケース  \n- つめ（左右）  \n- 突起（左右）  \n- 枠の角穴  \n\n取り付けの際は、大物ケースの左右の突起を枠の角穴に入れてセットしてください。また、小物ケース左右のつめを大物ケースの外側にセットしてください。  \n小物ケースはケース底面の「手前 FRONT」の文字とスリット(穴)がある方を手前にして取り付けてください。\n\n#### お知らせ  \n- 正しくセットされていないと、開閉時の異音や半ドアの原因になります。\n\n### 2 大物ケースを手前に持ち上げる  \n- 大物ケース  \n- 枠  \n- 小物ケース  \n- スリット（穴）  \n- 手前 FRONT  \n\n---\n\n## I 上段ケース・しきり・下段ケース（野菜室）\n\n### 1 ドアを手前いっぱいに開け、両端を手前に持ち上げ、さらにゆっくりと引き出し、床におろす  \n- 突起（左右）  \n- 枠の角穴  \n\n#### ご注意  \n- ドアを開けるときは足を近づけないようご注意ください。（足をドアにはさむおそれ）  \n- 下段ケース背面から水がたれる場合がありますのでご注意ください。  \n- 下段ケースを取りはずす前に必ずしきりを取りはずしてください。  \n\n正しくセットされていないと、開閉時の異音や半ドアの原因になります。  \nしきりを取り付けの際、「R」の文字を正面右下側にして、下段ケースに最後まで、しっかりと入れてください。  \n上段ケースはケース底面の「手前 FRONT」の文字がある方を手前にして取り付けてください。  \n\n#### お知らせ  \n- しきりや上段ケースが正しく取り付けられていないと、しきりやケース等の部品が破損することがあります。  \n取り付けた後は上段ケースのハンドルを持って操作し、正しく取り付けたことを確認してください。\n\n### 2 上段ケースを引き上げる  \n- 上段ケース\n\n### 3 しきりを取りはずす  \n- しきりの両側を持ってまっすぐ上に持ち上げてください。\n\n### 4 下段ケースを手前に持ち上げる  \n- 下段ケース  \n- しきり（R）  \n- 手前 FRONT  \n\n---\n\n## 引き出しドアの取りはずしかた・取り付けかた  \n（製氷室・冷凍室上段・冷凍室下段・野菜室）\n\n### 製氷室・冷凍室上段  \n- 枠などのイラスト\n\n### 冷凍室下段・野菜室  \n- 枠などのイラスト\n\n---\n\nページ番号: 27\n```",
    "metadata": {
      "topics": [
        "製氷ケースの取り外しと取り付け",
        "冷凍室下段ケースの操作方法",
        "野菜室の上段・下段ケースとしきりの扱い",
        "引き出しドアの取り外しと取り付け",
        "装着時の注意点とトラブル防止"
      ],
      "keywords": [
        "製氷ケース",
        "薄物ケース",
        "小物ケース",
        "大物ケース",
        "上段ケース",
        "下段ケース",
        "しきり",
        "引き出しドア",
        "手前 FRONT",
        "異音",
        "半ドア",
        "突起",
        "枠の角穴"
      ],
      "section_header": "ケースの取りはずしとかたち",
      "page_type": "maintenance"
    }
  },
  {
    "page": 28,
    "summary": "このページは冷蔵庫の不具合時の確認ポイントと対処法をまとめています。冷えない、霜や露がつくなどの問題に対し、設置状態やドアの開閉状況、温度設定の確認と適切な対応を促しています。トラブル時には記載されたページを参照し、必要なら相談窓口へ連絡するよう案内しています。",
    "content": "```markdown\n# お困りのときは\n\n修理を依頼される前に、次の点をもう一度お調べください。それでも具合の悪いときは、商品情報や使い方に関するご相談窓口にご連絡ください。→(P.35)  \n操作パネルが点滅している場合は、点滅している場所もご連絡ください。→(P.30)\n\n| こんなときは         | ここを確認してください                               | こうしてください。こういう理由です。                                               |\n|----------------------|----------------------------------------------------|-----------------------------------------------------------------------------------|\n| **使いはじめ**       |                                                    |                                                                                   |\n| よく冷えない         | 設置後、24時間以内ではありませんか？                | 設置直後は、冷えるまで24時間以上かかることがあります。食品はすき間をあけて収納し、開閉回数をできるだけ少なくしてお待ちください。なお、夏場や食品が多い場合は、冷えるまでさらに時間がかかります。 |\n| 製氷できない         | 設置後、24時間以内ではありませんか？                | 設置直後は、冷蔵庫全体が冷えていないため、最初の氷ができるまで24時間以上かかることがあります。食品はすき間をあけて収納し、開閉回数をできるだけ少なくしてお待ちください。            |\n| **冷えない**         |                                                    |                                                                                   |\n| 冷えないアイスクリームがやわらかい | 食品や袋がはさまり、半ドアになっていませんか？         | はさまっている食品を取り除き、しっかりとドアを閉めてください。なお、収納するときは、食品の高さに注意してください。               |\n|                      | 食品を無理に詰めたり、大量の食品を一度に入れていませんか？ | 食品はすき間をあけて収納してください。                                             |\n|                      | 各室のケースは正しく取り付けられていますか？       | 正しく取り付けてください。→(P.27)                                                |\n|                      | 冷蔵庫を設置した場所やすき間、周りの状況などによって冷えにくい場合があります。 | 正しく設置されているかご確認ください。→(P.6)                                     |\n|                      | 「節電モード」になっていませんか？                  | 「節電モード」を解除してください。→(P.22)                                        |\n|                      | 温度設定が「弱め」になっていませんか？              | よく冷えない部屋の温度設定を変更してください。→(P.10, 17)                         |\n|                      | 夏場など、冷蔵庫の周囲の温度が高くなっていませんか？ |                                                                                   |\n|                      | ドアを長い間、開けていたり、頻繁にドアの開閉をしていませんでしたか？ | 冷蔵庫のドアを開けている間は庫内の温度が少しずつ上がります。開閉が頻繁または長い時間ドアを開けたままにしておくと、庫内の温度が下がりにくくなります。ドアを開けている時間を短くしたり、開閉回数をできるだけ少なくしてください。 |\n|                      | 操作パネルの点灯しているランプが次々と変わっていませんか？ | 店頭用モードに入っていますので、解除してください。→(P.30)                      |\n| **霜や露がつく**     |                                                    |                                                                                   |\n| 庫内や引き出しの枠に霜や露、氷がつく | 一時的に冷蔵室ドアや引き出しドアが半ドアになっていませんでしたか？ | ドアを閉める際は食品や袋がはさまっていないかを確認し、しっかりと閉めてください。                 |\n|                      | ドアを長い間、開けていたり、頻繁にドアの開閉をしていませんでしたか？ | ドアを閉閉したときに、空気中にふくまれる水分が、霜や氷となって、冷凍室の壁面や部品につくことがあります。ドアを開けている時間を短くしたり、開閉回数をできるだけ少なくしてください。霜や露は乾いた布でふき取ってください。 |\n| 冷蔵庫の外側に露がつく | 冷蔵庫の周囲の湿度が高くなっていませんか？          | 雨の日など湿度が高いときは、露がつくことがあります。露は乾いた布でふき取ってください。        |\n|                      | 温度設定が「チルド」や「強め」になっていませんか？ | 温度設定が「チルド」や「強め」のときはドア表面に露がつくことがあります。温度設定を「標準」にしてください。露は乾いた布でふき取ってください。→(P.10, 17) |\n| 冷蔵庫背面及び壁に露がつく | 冷蔵庫周囲の湿度が高く、冷蔵庫背面と壁とのすき間が狭くなっていませんか？ | 冷蔵庫背面を壁から2cm以上離してください。→(P.6)                               |\n| 冷蔵室の中が結露する | ドアを長い間、開けていたり、頻繁にドアの開閉をしていませんでしたか？ | ドアの開閉回数が多いときや、冷蔵庫の周囲の湿度が高いときは壁などが曇ったり、冷気吹き出し口の周り→(P.10)に露がつくことがあります。故障ではありません。乾いた布でふき取ってください。              |\n\n![結露の図](画像内右下に結露を示す図があります。)\n```\n",
    "metadata": {
      "topics": [
        "冷蔵庫の冷却不良",
        "製氷問題の対応",
        "霜・結露の発生原因と対処",
        "操作パネルの点滅対応",
        "設置時の注意点"
      ],
      "keywords": [
        "冷蔵庫",
        "冷えない",
        "製氷できない",
        "霜",
        "露",
        "結露",
        "操作パネル点滅",
        "節電モード",
        "ドア半開き",
        "設置後24時間"
      ],
      "section_header": "お困りのときは",
      "page_type": "troubleshooting"
    }
  },
  {
    "page": 29,
    "summary": "このページは自動製氷機能に関するトラブルシューティング表で、氷ができない、できにくい、氷の品質に関する問題について原因と対処法を具体的に示しています。給水タンクの水量不足や製氷停止設定、ドアの開閉状況などが主なチェックポイントです。異常ではない現象や注意すべき操作方法も説明されています。",
    "content": "```markdown\n| こんなときは           | ここを確認してください                                                                                                  | こうしてください。こういう理由です。                                                                                                                |\n|-----------------------|---------------------------------------------------------------------------------------------------------------------|---------------------------------------------------------------------------------------------------------------------------------------------------|\n| **氷がまったくできない** | 操作パネルの「製氷停止」ランプが点灯していませんか？ 製氷停止に設定されています。                                                      | 「製氷」または「急速製氷」に設定してください。→(**P.14, 15**)                                                                                      |\n|                       | 給水タンクの水が少なくなっていませんか？                                                                                     | 水の残りが少なくなると氷ができないことがあります。給水タンクの満水線まで水を入れてください。→(**P.14**)                                            |\n|                       | 給水タンクが「タンクセット位置」の線を越えるまで奥にしっかりと押し込まれていますか？                                             | 給水タンクを「タンクセット位置」の線を越えるまで奥に押し込んでください。→(**P.14**)                                                               |\n|                       | 製氷ケースに氷以外のものが収納されていませんか？                                                                                | 製氷ケースから取り除いてください。                                                                                                                 |\n| **氷がなかなかできない** | 氷が部分的に満氷線を越えてたまっていませんか？                                                                                   | 氷をならしてください。→(**P.15**)                                                                                                                  |\n|                       | ドアを頻繁に開ける、大量の食品を一度に収納するなどしていませんか？                                                                 | 庫内が十分に冷えていません。庫内が冷えるまでできるだけドアの開閉を少なくしてください。収納している食品同士の間隔をできるだけあけてください。                                          |\n|                       | 冷蔵庫の周囲の温度が低くなっていませんか？                                                                                     | 冬場は、氷ができるまで4時間以上かかることがあります。ドアの開閉回数をできるだけ少なくしてお待ちください。                                         |\n|                       | 「製氷停止」の設定から「製氷」の設定に変更した直後ではありませんか？                                                               | 設定を変更した直後は時間がかかることがあります。ドアの開閉回数をできるだけ少なくしてお待ちください。                                               |\n|                       | 食品や袋がはさまり、冷凍室や製氷室が半ドアになっていませんか？                                                                      | はさまっている食品は取り除き、しっかりとドアを閉めてください。                                                                                      |\n|                       | 「節電モード」になっていませんか？                                                                                            | 「節電モード」を解除してください。→(**P.22**)                                                                                                      |\n| **氷に突起ができる**    | ―                                                                                                                   | 製氷皿の薄部分にたまった水が凍ったものです。異常ではありません。                                                                                   |\n| **ためた氷が丸くなる氷同士がくっつく** | 古い氷をためたままにしていませんか？                                                                                            | 古い氷は自然に小さくなったりくっついたりします。製氷スコップなどで氷が離れる程度であれば問題はありません。                                         |\n|                       | ドアを頻繁に開ける、大量の食品を一度に収納するなどしていませんか？                                                                 | ドアを開けている時間を短くしたり、開閉回数をできるだけ少なくしてください。                                                                         |\n|                       | 一時的に冷蔵室ドアや引き出しドアが半ドアになっていませんでしたか？                                                                  | ドアを閉めるときは、しっかりと最後まで閉めてください。                                                                                              |\n| **できあがった氷が小さい** | 給水タンクの水が少なくなっていませんか？                                                                                     | 水の残りが少なくなると、小さな氷ができることがあります。給水タンクの満水線まで水を入れてください。→(**P.14**)                                    |\n| **できあがった氷がはじめからくっついている** | ―                                                                                                                   | 製氷皿の溝部分にたまった水が凍り氷同士がくっつくことがあります。異常ではありません。                                                               |\n| **氷に白いにごりがある** | ミネラルウォーターで氷をつくっていませんか？                                                                                    | 水の中に溶け込んでいた空気の細かい泡が氷の中に閉じこめられたためです。水にふくまれるミネラル分が凍って白くにごることがありますが、害はありません。                                   |\n| **氷をつくらないときは** | ―                                                                                                                   | 「製氷停止」に設定してください。「氷をつくらない（製氷停止）」をご覧ください。→(**P.15**)                                                           |\n\n---\n### 自動製氷\n（表全体が「自動製氷」に関する内容）\n```\n",
    "metadata": {
      "topics": [
        "自動製氷",
        "トラブルシューティング",
        "製氷機能の問題",
        "氷の品質",
        "給水タンクの管理"
      ],
      "keywords": [
        "自動製氷",
        "製氷停止",
        "給水タンク",
        "満水線",
        "節電モード",
        "製氷ケース",
        "氷のくっつき",
        "氷の白いにごり",
        "ドアの閉まり",
        "急速製氷"
      ],
      "section_header": "自動製氷",
      "page_type": "troubleshooting"
    }
  },
  {
    "page": 30,
    "summary": "このページは、冷蔵庫の故障や異常時の確認ポイントと対処法を詳しく説明しています。操作パネルのランプ点滅の意味や製氷機の問題、ドアの開閉不良、店頭用モードの解除方法などが記載されています。また、野菜室の結露やドア開閉時のケースの位置などの注意点についても具体的に解説されています。",
    "content": "```markdown\n# お困りのときは ～つづき～\n\n| こんなときは | ここを確認してください | こうしてください。こういう理由です。 |\n| --- | --- | --- |\n| **操作パネルのランプが点滅している** | 「節電」と冷凍「強め・標準・弱め」と冷蔵「チルド・標準・弱め」の7つのランプのうち、どのランプが点滅しているか確認してください。 | 右のチェックリストを使い、点滅しているランプに☑マークを付けて修理に関するご相談窓口にご連絡ください。→(P.35) ☑マークを付けた番号（①～⑦）をご相談窓口にお知らせください。<br>**（チェックリスト）**<br>②☐強め ⑤☐チルド<br>③☐標準 ⑥☐標準<br>①☐節電 ④☐弱め ⑦☐弱め<br>節電　冷凍　冷蔵 |\n| 「製氷」ランプ点滅または冷凍「強め・弱め」と冷蔵「弱め」ランプ点滅 | 製氷室に自動製氷機でつくった氷以外の食品や氷を入れていませんか？ | 製氷皿に、食品などがあたっている可能性があります。製氷室を空にして「製氷おそうじ」を実施してください。→(P.25) |\n| 「急速製氷」「製氷」「製氷停止」ランプ同時点滅 | 製氷を5秒以上押しませんでしたか？ | 「製氷おそうじ」を行っています。<br>約4分間で「製氷おそうじ」が終了し、「製氷」ランプが点灯します。「製氷おそうじ」は中止できません。<br>「製氷おそうじ」をご覧ください。→(P.25) |\n| すべてのランプ点滅 | ドアが開いていませんか？ドアに食品などがはさまって半ドアになっていませんか？ | ドアが開いている場合は、閉めてください。<br>食品などがはさまって半ドアになっている場合は、取り除いてしっかりと閉めてください。 |\n| 点灯しているランプが次々と変わっている | ― | 店頭用モードに入っていますので以下の解除操作をしてください。店頭用モードのときは冷却運転をしません。<br>まず、冷蔵室ドア、冷凍室下段ドアを開けてください。<br>次に、いずれかのボタンを押し設定表示にしてから、【冷凍】をピピッと鳴るまで10秒以上押しつづけてください。<br>数秒間すべてのランプが点灯し店頭用モードが解除され、冷却運転を開始します。<br>最後に、すべてのドアを閉めてください。 |\n\n| こんなときは | ここを確認してください | こうしてください。こういう理由です。 |\n| --- | --- | --- |\n| **野菜室が気になる** |  |  |\n| 野菜室の中が結露する | 水分の多い野菜を大量に収納していませんか？ | 野菜室はほかの部屋に比べて、湿度が高くなっているため、野菜の量や種類によって野菜室のケースや天井、食品表面に結露することがあります。異常ではありません。結露が気になるときは、ラップをかけて収納することをおすすめします。また、結露が多くなると、野菜室のケースに水がたまる場合があります。たまった水はやわらかい布でふき取ってください。 |\n| うるおいユニットが食品の袋や容器によってふさがれていませんか？ | うるおいユニットがふさがれていると、結露が発生しやすくなります。うるおいユニットをふさいでいる食品の袋や容器を他の場所に移動してください。結露はやわらかい布でふき取ってください。 |\n| 野菜室のドアが閉まらない・野菜室のドアを開けたとき上段ケースがロックの位置に戻らない |  |  |\n| しきりが正しい方向でついていますか？ | しきりを正しい方向に取り付けてください。→(P.27) |\n| 上段ケースと下段ケースの間に食品などがはさまっていませんか？ | はさまっているときは取り除いてください。<br> ![イラスト](画像内イラスト参照) |\n| 上段ケースのハンドル部にペットボトル、食品などがあたっていませんか？ | ハンドルに、ペットボトル、食品があたらないように保管してください。<br> ![イラスト](画像内イラスト参照) |\n| 上段ケースと野菜室の天井の間に食品などがはさまっていませんか？ | はさまっているときは取り除いてください。<br>また、野菜室の天井に食品などがあった状態で無理にドアを閉めないでください。<br> ![イラスト](画像内イラスト参照) |\n\n---\n\n30\n```\n",
    "metadata": {
      "topics": [
        "操作パネルのランプ点滅トラブル",
        "製氷機のトラブル対処",
        "ドアの開閉不具合",
        "野菜室の結露と対処",
        "野菜室のドアとケースの取り扱い"
      ],
      "keywords": [
        "操作パネル",
        "ランプ点滅",
        "節電ランプ",
        "製氷ランプ",
        "急速製氷",
        "製氷おそうじ",
        "店頭用モード",
        "野菜室",
        "結露",
        "しきり",
        "ドアロック"
      ],
      "section_header": "お困りのときは ～つづき～",
      "page_type": "troubleshooting"
    }
  },
  {
    "page": 31,
    "summary": "このページは冷蔵庫の特鮮氷温ルームの水滴や霜、ドアの段差や傾き、におい、冷え過ぎ、庫内の熱さなどのトラブルや疑問に対して、原因の確認ポイントと対処方法を詳しく説明しています。主な対策としては食品の密封や適切な温度設定、設置環境の調整などが挙げられ、安全上の問題はないことも明示しています。",
    "content": "```markdown\n| こんなときは気になる                         | ここを確認してください                                                  | こうしてください。こういう理由です。                                                                                                                                                                  |\n|----------------------------------------------|--------------------------------------------------------------------------|-------------------------------------------------------------------------------------------------------------------------------------------------------------------------------------------------------|\n| **特鮮氷温ルームが気になる**                 | **特鮮氷温ルームの内部や特鮮氷温ケース周辺に水滴や霜、氷がつく**         | 食品や空気中に含まれる水分により、ルーム内に露や霜がつくことがあります。<br>水分の多い食品はラップしていただくことをおすすめします。水滴や霜がついた場合はやわらかい布にぬるま湯をふくませてふき取ってください。                  |\n|                                              | 水分の多い食品を収納していませんか？                                    | ![水滴や霜のイラスト](画像中イラスト)                                                                                                                                                                  |\n| **ドアの段差や傾きが気になる**                 | **左右のドアに段差があるドアが傾いている**                              | 設置場所は水平ですか？                                                                                                                  | 性能上問題なくそのままお使いいただけますが、気になるときは、左右の調節脚で調整してください。→(P.6)                                                                                                   |\n|                                              | 床材がやわらかく、収納物の重みが加わり脚が沈んでいませんか？            | 冷蔵庫本体が傾く場合は、厚さ1cm以上の丈夫な板を敷いてください。                                                                                                                                      |\n| **においが気になる**                         | **プラスチックのにおいがする**                                          | ———                                                                                                                                    | 庫内にプラスチック部品を多く使用しているためですが、十分に冷えるにしたがってにおいは徐々に少なくなります。異常ではありません。                                                                       |\n|                                              | **氷がにおう**                                                          | 給水タンク、浄水フィルターが汚れたり、氷が古くなっていませんか？                  | 「ぬめり」「水アカ」防止のため、定期的に水洗いしてください。→(P.24, 25)                                                                                                                                |\n|                                              |                                                                          | ———                                                                                                                                    | 水道水中の塩素分が凝縮されるため、塩素が強くにおうことがあります。                                                                                                                                      |\n|                                              | **庫内がにおう**                                                        | においの強い食品をそのまま収納していませんか？                                  | 脱臭機能はすべてのにおいを完全に取り除くことはできません。ラップをかけるなど密封して収納してください。                                                                                                 |\n| **冷え過ぎる・凍ってしまう**                 | **冷え過ぎる・凍ってしまう**                                            | 温度設定が「チルド」や「強め」になっていませんか？                              | 温度設定を「標準」にしてください。→(P.10, 17)                                                                                                                                                           |\n|                                              | 周囲温度が5℃以下ではありませんか？                                    | 周囲温度が低いときは庫内が冷え過ぎることがあります。温度設定を「弱め」にしてください。                                                                                                              |\n|                                              | 冷気吹き出し口の前に置いていませんか？                                | 冷気吹き出し口の前には置かないでください。蓋やラップをすることで食品の凍結を抑えることができます。                                                                                                |\n| **冷蔵庫が熱くなる**                         | **冷蔵庫の側面やドアのふち部分が熱くなる 足元から暖かい風が出る**          | ———                                                                                                                                    | 冷却装置が運転するときに発生する熱を外に逃がすために熱くなることがあります。設置直後や夏場は50～60℃になることもあります。安全および性能上問題はありませんが、手を触れないでください。                                                    |\n\n---\n\nお困りのときは\n```",
    "metadata": {
      "topics": [
        "特鮮氷温ルームの結露・霜対策",
        "ドアの段差・傾きへの対応",
        "庫内や氷のにおいの原因と対策",
        "冷蔵庫の冷えすぎ問題",
        "冷蔵庫の熱発生と安全上の注意"
      ],
      "keywords": [
        "特鮮氷温ルーム",
        "水滴",
        "霜",
        "ドア調整脚",
        "におい",
        "氷のにおい",
        "温度設定",
        "冷え過ぎ",
        "庫内脱臭",
        "冷蔵庫側面の熱"
      ],
      "section_header": "お困りのときは",
      "page_type": "troubleshooting"
    }
  },
  {
    "page": 32,
    "summary": "このページは冷蔵庫の音に関するトラブルシューティングガイドであり、音がうるさい場合の原因や対処法を詳細に説明しています。また、冷蔵庫から聞こえる様々な音の種類とそれが正常な動作に伴う音であることを解説し、ユーザーの不安を解消する内容となっています。",
    "content": "```markdown\n# お困りのときは ～つづき～\n\n| こんなときは           | ここを確認してください                                                | こうしてください。こういう理由です。                                           |\n|------------------------|----------------------------------------------------------------------|-------------------------------------------------------------------------------|\n| 音がうるさい            | ![音声マーク](音声アイコン)マークがある項目はホームページから音が確認いただけます。 |                                                                               |\n|                        | 床がたわんでいませんか？                                             | 冷蔵庫が振動して運転音が大きくなることがあります。厚さ1cm以上の丈夫な板を敷いてからその上に設置してください。→(P.6) | ―                                                                             |\n|                        | 冷蔵庫が壁や家具などにあたっていませんか？                           | 運転音が共振して音が大きくなることがあります。冷蔵庫の周りにすき間をあけて設置してください。                   | ―                                                                             |\n|                        | 脚カバーが外れていませんか？                                         | 運転音が共振して音が大きくなることがあります。脚カバーはしっかり取り付けてください。→(P.6)                  | ―                                                                             |\n|                        | こんなときではありませんか？                                        |                                                                               |\n|                        | ・使いはじめなど、冷蔵庫内が冷えていないとき                            | 庫内を早く冷やすため、モーターやコンプレッサーが高速運転して音が大きくなることがあります。十分に冷えれば音は小さくなります。 | ![音声マーク](音声アイコン)                                                       |\n|                        | ・ドアの開け閉めが多いとき                                          |                                                                               |\n|                        | ・周囲の温度が高いとき                                              |                                                                               |\n|                        | ・「急速製氷」や「クイック冷却」「急冷凍」に設定しているとき         |                                                                               |\n| 音が気になる           | 音が長くつづく                                                      | ―                                                                     | コンプレッサーをゆっくり運転させて、省エネ運転をしているため、音が長くつづくことがあります。                          | ―                                                                             |\n|                        | ときどき音が大きくなる                                            | ―                                                                     | 庫内の温度変化に合わせて運転する力を調節しているため、ときどき音が大きくなることがあります。                             | ―                                                                             |\n| こんな音がしたときは（異常ではありません） | 通常時に聞こえる音（ブーン、ボー、キーん、コトコト、ウィーン）        | 庫内を冷やすためにモーターやコンプレッサーが動く音です。                               | ![音声マーク](音声アイコン)                                                       |\n|                        | 衝突するような音（コツコツ）                                        |                                                                               | 庫内を冷やすための冷媒が流れる音です。                                             | ![音声マーク](音声アイコン)                                                       |\n|                        | 沸騰するような音（ボコボコ、ぶつぶつ）                               |                                                                               |                                                                             | ![音声マーク](音声アイコン)                                                       |\n|                        | 炭酸が弾けるような音（シュワシュワ、チリチリ）                       |                                                                               |                                                                             | ![音声マーク](音声アイコン)                                                       |\n|                        | 水の流れるような音（チョロチョロ）                                   | 霜取りの際に水が流れたり、蒸発したりする音です。                               | ―                                                                             |\n|                        | 肉を焼くような音（ジュー）                                         |                                                                               |                                                                             | ―                                                                             |\n|                        | きしむような音（ピシッ、ギシッ）                                   | 庫内の温度が変化するときに部品が膨張してきしむ音です。                           | ![音声マーク](音声アイコン)                                                       |\n|                        | 引っかかるような音（コトコト）                                     |                                                                               | 庫内の温度を制御する電気部品が作動する音です。                                    | ![音声マーク](音声アイコン)                                                       |\n|                        | うなるような音（ブー）                                             |                                                                               |                                                                             | ![音声マーク](音声アイコン)                                                       |\n|                        | 衝突するような音（ガラガラ、ゴトゴト）                             | 自動製氷機の製氷皿から氷が落ちる音です。                                     | ![音声マーク](音声アイコン)                                                       |\n|                        | 水の流れるような音（ギューイン、ゴボゴボ）                         | 自動製氷機の製氷皿に水を入れる音です。氷をつくらないときは、製氷を押して「製氷停止」にしてください。 | ![音声マーク](音声アイコン)                                                       |\n|                        | ときどきする音（カチッ、ウィーン、カツカツカツ、ブーン、キーん、カタカタ、ジリジリ） | 庫内を冷やすための部品が動いている音です。                                   | ![音声マーク](音声アイコン)                                                       |\n\nページ番号: 32\n```\n",
    "metadata": {
      "topics": [
        "冷蔵庫の運転音",
        "音の原因と対策",
        "異音の種類と説明",
        "正常な運転音の識別"
      ],
      "keywords": [
        "冷蔵庫",
        "運転音",
        "振動",
        "脚カバー",
        "モーター",
        "コンプレッサー",
        "製氷機",
        "異音",
        "共振",
        "音の確認"
      ],
      "section_header": "お困りのときは",
      "page_type": "troubleshooting"
    }
  },
  {
    "page": 33,
    "summary": "このページは冷蔵庫のよくあるトラブルと対処方法、および冷蔵庫の移動・運搬準備について説明しています。静電気や電磁波に関する注意、製造上の外観のゆがみや穴の説明、停電時の対応、長期間使用しない場合の手入れ方法などが記載されています。また、引っ越し時の食品や水の取り出し、プラグの抜き方、運搬時の注意点も詳しく案内しています。",
    "content": "```markdown\n| こんなときは                           | こうしてください。こういう理由です。                                                                                                                                                         |\n|--------------------------------------|---------------------------------------------------------------------------------------------------------------------------------------------------------------------------------------------|\n| **本体に触れるとわずかに電気を感じる** | 冷蔵庫が静電気を帯びる場合がありますが、安全上問題はありません。気になる場合はアースの取り付けをおすすめします。→(P.7)                                                                        |\n| **テレビ・ラジオなどに雑音、映像の乱れが生じる** | この冷蔵庫からごくわずかに発生する電磁波のためです。テレビ・ラジオ・インターフォンなどから離して設置してください。アンテナ線などから離れたところの電源を使用し、アースの取り付けをおすすめします。→(P.7)                        |\n| **プラスチック部品に傷のような細い線がある**     | プラスチックを成形する際に発生する樹脂の流れの跡です。透明な部品について特に目立ちやすくなっていますが、強度上の問題はなく割れに至ることはありません。                                                               |\n| **ドア面や側面・天面にゆがみがある**               | 冷蔵庫の製造工程上、ゆがみが生じます。光源の位置や明るさなどによっては目立つことがありますが、異常ではありません。また、性能上問題ありません。                                                                       |\n| **ドア内側や冷蔵室側面に小さな穴が開いている**       | この穴は冷蔵庫の製造工程にて断熱材を充填する際に内部の空気を逃がすための穴です。傷や異常ではありません。                                                                                                                                               |\n|                                      | ![穴(ドア内側)](image)  ![穴(冷蔵室側面)](image)                                                                                                                                            |\n|                                      | ※製品によっては、シールが貼ってある場合がありますが、剥がさずにご使用ください。                                                                                                                                                              |\n| **停電した**                          | 復旧するまでの間はドアの開閉を減らし、新たな食品の収納はさけてください。停電復旧した後は、停電により各設定（温度設定や製氷モードの設定など）が変わる場合がありますので、再び設定してください。                                                          |\n| **冷蔵庫を長期間使わない**                | 庫内の食品をすべて出してください。電源プラグを抜いて庫内や自動製氷機のお手入れをしてください。→(P.23～25)  2～3日間すべてのドアを開けて乾燥させてください。                                                               |\n| **霜取りをする**                     | この冷蔵庫は自動で霜取りをしますので、操作は必要ありません。解けた水は蒸発皿にたまり、自動的に蒸発します。                                                                                                                                |\n| **冷蔵庫を移動・運搬する**               | 「移動・運搬の準備（引っ越しをする）」をご覧ください。→(下記参照)                                                                                                                                                                      |\n| **ガラスが割れた（ガラス棚）**           | 割れたガラスに触れず、すぐにお買い上げの販売店にご相談ください。                                                                                                                                                                              |\n| **ドアを閉めるとほかのドアが開く**            | ドアを勢いよく、閉めませんでしたか？各室は冷気通路でつながっているため、ドアを閉める風圧で他のドアが一瞬開くことがあります。                                                                                                                |\n| **ドアを閉めた直後開けようとすると重い**         | ドアを長い間、開けていませんでしたか？庫内に入った空気が急に冷やされて、圧力が一時的に庫外よりも低くなるためです。しばらくお待ちいただいてからドアを開けてください。                                                                   |\n| **振動音が気になるときや、湿気による背面壁の変色・汚れが気になるとき** | 背面壁から離して（2cm以上）設置してください。→(P.6)                                                                                                                                                                                  |\n\n---\n\n# 移動・運搬の準備（引っ越しをする）\n\n1. **食品や氷を取り出す**\n\n2. **給水タンク・製氷皿の水をすてる**  \n   給水タンクをはずして「製氷おそうじ」をしてください。→(P.25)\n\n3. **電源プラグを抜く**  \n   移動直前でも問題ありません。\n\n4. **脚カバーを取りはずし、調節脚を上げる** →(P.6)\n\n5. **ドア・電源プラグ・コードをテープで固定する**\n\n6. **移動・運搬時には保護用のシート・布などを敷く**  \n   床材を傷つけたり、水がこぼれたりすることを防ぐためです。\n\n7. **冷蔵庫の下に布などを敷き、冷蔵庫を後方に倒して、背面下部より水抜きをする**  \n   ![布など](image)\n\n8. **運搬用取っ手を持ち、2人以上で運ぶ**  \n   ● ご注意  \n   輸送のときは横積みしないでください。  \n   （冷蔵庫の故障の原因）  \n   ![2人で運搬するイメージ](image)\n\n9. **「使いはじめるまでの手順」に従って設置する** →(P.6,7)\n\n---\n\n**ご注意**  \n移動や運搬をするときは、冷蔵庫をぶつけないようにご注意ください。（冷蔵庫や家財を傷つけるおそれ）\n```\n",
    "metadata": {
      "topics": [
        "冷蔵庫のトラブル対処法",
        "電磁波と静電気の注意",
        "冷蔵庫の製造上の特性",
        "停電時の対応",
        "移動・運搬の準備と注意点"
      ],
      "keywords": [
        "冷蔵庫",
        "静電気",
        "電磁波",
        "停電",
        "霜取り",
        "引っ越し",
        "運搬",
        "製氷機",
        "アース",
        "背面設置距離"
      ],
      "section_header": "トラブルシューティング",
      "page_type": "troubleshooting"
    }
  },
  {
    "page": 34,
    "summary": "このページは冷凍冷蔵庫R-HWS47X・R-HWS47XLの仕様書で、容量や寸法、消費電力量、冷凍室の性能、収納できる食品の耐荷重など詳細なスペックを表形式で示しています。年間消費電力量はJIS規格に基づき測定され、設置環境や使用条件によって変動することが説明されています。また、食品の保管温度区分と推奨保存期間の目安も記載されています。",
    "content": "```markdown\n# 仕様\n\n| 型式                    | R-HWS47X・R-HWS47XL |\n|-------------------------|---------------------|\n| 種類                    | 冷凍冷蔵庫          |\n| 定格内容積〈食品収納スペースの目安〉[L] |                     |\n| 全定格内容積            | 470                 |\n| 冷蔵室                  | 243（188）          |\n| うち特鮮氷温ルーム      | ＜13＞              |\n| 製氷室（ツースター）    | 22＜7＞             |\n| 冷凍室上段（ツースター）| 23＜12＞            |\n| 冷凍室下段（フォースター）| 95＜62＞            |\n| 野菜室                  | 87＜58＞            |\n| 外形寸法[mm]            |                     |\n| 幅                      | 600                 |\n| 奥行                    | 701                 |\n| 高さ                    | 1,833               |\n| 定格電圧[V]             | 交流100             |\n| 定格周波数[Hz]          | 50／60 共用         |\n| 電動機の定格消費電力[W] | 95                  |\n| 電熱装置の定格消費電力[W]| 155                 |\n| 年間消費電力量          | 冷蔵室ドア内側の品質表示ラベルに表示してあります。 |\n| 質量[kg]                | 93                  |\n\n- 定格内容積は、日本産業規格（JIS C9801-3:2015）に基づき、庫内の温度制御に必要でない庫内容器（棚やケース等）を取りはずした状態で算出したものです。\n- 食品収納スペースの目安は、日本産業規格（JIS C9801-3:2015）に基づき、庫内容部品を取り付けた状態で算出したものです。\n- 貯蔵室ごと（例えば、冷蔵室、冷凍室、野菜室等）に、定格内容積と併せ食品収納スペース（貯蔵室ごとに実際に食品を収納することができる空間的容積）の目安を表示しています。\n- 冷蔵室の食品収納スペースの目安には特鮮氷温ルームの数値を含みます。\n- ＜＞内は、消費電力量計測での各室の目標温度の区分を示しています。目標温度の区分は日本産業規格（JIS C 9801-1:2015および9801-3:2015）に定められています。\n- この製品は日本国内家庭用です。電源電圧や電源周波数の異なる海外では使用できません。またアフターサービスもできません。\n\n---\n\n## 消費電力量について\n\n年間消費電力量は、JIS C 9801-3:2015 測定基準によります。  \n使用時の消費電力量は、設置の仕方、各庫内の温度設定、周囲温度や湿度、ドア開閉頻度、新しく入れる食品の量や温度、使い方などにより変動します。\n\n### 年間消費電力量測定方法の概要\n\n| 種類            | 冷凍冷蔵庫                                  |\n|-----------------|---------------------------------------------|\n|                 | [スリースター][フォースター]機種           |\n| 庫内温度        | 冷凍室   | 冷蔵室   | 冷蔵室  | 冷凍室      |\n|                 | −18℃以下 | 4℃以下  | 4℃以下 | −18℃以下   |\n| 周囲温度        | 32℃及び16℃                                |\n| 周囲湿度        | 32℃測定時：70±5％、16℃測定時：55±5％       |\n| 消費電力量の表示| 年間消費電力量（kWh／年）                   |\n|                 | （周囲温度32℃測定による1日当たりの消費電力量205日分と周囲温度16℃測定による1日当たりの消費電力量160日分の合計） |\n\n---\n\n## 冷凍室の性能\n\n冷凍室の性能は、日本産業規格（JIS C9607）に定められた方法で試験したときの、冷凍負荷温度（食品温度）によって表示しています。\n\n| 記号   | ★★★（フォースター） | ★★（ツースター） |\n|--------|----------------------|-------------------|\n| 冷凍負荷温度（食品温度） | −18℃以下               | −12℃以下           |\n| 市販冷凍食品の貯蔵期間の目安 | 約3カ月                 | 約1カ月             |\n\n※市販冷凍食品の貯蔵期間  \n冷凍食品の貯蔵期間は、食品の種類・店頭での貯蔵状態・冷蔵庫の使用条件などによって異なりますので、一応の目安としてご覧ください。\n\n---\n\n# 収納できる食品の重さの目安\n\n収納できる食品の重さには制限があります。収納する食品の重さの合計が、各棚、ケースの目安を超えないようにしてください。  \n※耐荷重（部品が破損しない食品の重さ）を表示しています。\n\n| 部品名                 | R-HWS47X・R-HWS47XL |\n|------------------------|---------------------|\n| 冷蔵室                 |                     |\n| 高さかわるん棚上段      | 15.5                |\n| 高さかわるん棚中段      | 15.5                |\n| 高さかわるん棚下段・固定棚| 15.5                |\n| 特鮮氷温ルーム上の棚    | 8.0                 |\n| 特鮮氷温ケース          | 4.0                 |\n| ドアポケット合計        | 21.5                |\n| 製氷室                 | 製氷ケース（貯氷スペースには自動製氷機でつくった氷以外は入れないでください →（P.35）） |\n| 冷凍室上段              | 上段フリーザーケース | 4.0                 |\n| 冷凍室下段              | 薄物ケース          | 4.0                 |\n|                         | 小物ケース          | 5.0                 |\n|                         | 大物ケース          | 12.0                |\n| 野菜室                 | 上段ケース          | 4.5                 |\n|                         | 下段ケース          | 14.5                |\n\n単位：[kg]\n```\n",
    "metadata": {
      "topics": [
        "製品仕様詳細",
        "消費電力量の測定方法",
        "冷凍室の性能指標",
        "食品収納スペースと重さの目安",
        "JIS規格に基づく表示"
      ],
      "keywords": [
        "R-HWS47X",
        "R-HWS47XL",
        "冷凍冷蔵庫",
        "定格内容積",
        "消費電力量",
        "JIS C9801-3:2015",
        "特鮮氷温ルーム",
        "製氷室",
        "冷凍負荷温度",
        "耐荷重"
      ],
      "section_header": "仕様",
      "page_type": "specification"
    }
  },
  {
    "page": 35,
    "summary": "このページは冷蔵庫の別売部品の購入方法と価格、お客様相談窓口の連絡先・受付時間、修理依頼手続き、個人情報の取り扱いについて説明しています。また、長期間使用した冷蔵庫の点検の重要性や廃棄時のリサイクル法に基づく注意事項についても案内しています。",
    "content": "```markdown\n# 別売部品\n■ 次の部品を購入する場合は、必ず販売店にお使いの冷蔵庫の型式をご指定のうえ、専用の部品をお買い求めになってください。\n\n| こんなとき | 商品名 | 型式 | 商品型式 | 希望小売価格 |\n| --- | --- | --- | --- | --- |\n| 氷がにおうとき 浄水フィルターが古く汚れているおそれがあります。 (使用期限の目安は約3~4年です) | 自動製氷用浄水フィルター | 全機種共通 | RJK-30 | 1,980円(税込) |\n| 地震にそなえて | 冷蔵庫用地震軽倒防止ベルト ※2セット必要となります。 | 全機種共通 | R-826CV 300 | 1,144円(税込) ※1セットの価格です |\n| ドアの段差や傾きが気になるとき | 調整板(3枚) | 全機種共通 | R-Y6000 500 | 1,320円(税込) |\n\n※上記の希望小売価格は、価格改正に伴い変更する場合があります。\n\n---\n\n# お客様ご相談窓口\nこの製品の使いかた・お手入れ・修理などは、お買い上げの販売店へご相談ください  \nまたは「日立家電についてのご相談窓口」(下記)にご相談ください。  \n※下方の内容は予告なく変更させていただく場合がございます。最新情報は、日立家電サポートページをご確認ください。\n\nご相談の前に本取扱説明書の「お困りのときは」をご確認ください。  \nまた日立家電サポートページで、「よくあるご質問」や「使いかた動画」など各種情報をご覧いただけます。\n\n[日立家電 サポート 検索] [QRコード]\n\n---\n\n## 商品情報や使い方に関するご相談\n（機能・操作・設定などのご相談ができます）\n電話のほかLINE、チャット、メールなど様々なお問合せ方法を準備しております。  \n詳しくは日立家電サポートページをご覧ください。\n\n**TEL** 0120-3121-11  \n**携帯電話** 050-3155-1111 (有料)  \n**FAX** 050-3135-2134 (有料)  \n\n■受付時間：9:00〜17:30 (月〜金)  \n（土曜・日曜・祝日、年末年始は休業）\n\n---\n\n## 修理に関するご相談\n（修理のご依頼やご相談ができます）\n\n24時間受付希望の方は  \n「Web受付」へ  \n[日立家電 修理 Web 検索] [QRコード]\n\n電話、FAXで受付希望の方は  \n「お電話受付」へ  \n\n**TEL** 0120-3121-68  \n**携帯電話** 0570-0031-68 (有料)  \n**FAX** 0570-2006-57 (有料)  \n\n■受付時間：9:00〜18:00 (月〜土)  \n       9:00〜17:00 (日、祝日)\n\n---\n\n# 部品のご購入について\n部品のご購入は、商品お買い上げの販売店、お近くの日立の家電品取扱店（お取り寄せ）または「パーツショップ」へご依頼ください。\n\n[https://store.kadenfan.hitachi.co.jp/store/pages/parts.aspx](https://store.kadenfan.hitachi.co.jp/store/pages/parts.aspx)  \n[日立家電 部品 検索] [QRコード]\n\n- 通話内容の確認と応対品質向上のため、録音させていただきます。  \n- 予期せぬ障害などでお電話が切れてしまった際、折り返し電話を差し上げられるよう、発信者番号の通知をお願いします。「非通知」設定されているお客様は、はじめに「186」をダイヤルしておかけください。  \n- 営業時間外やお電話が繋がりにくい場合は、時間を変えてお掛け直しをお願いします。  \n- 修理ご依頼の前に、当社の修理対応方針につきまして、「修理ご利用規約」をご覧ください。  \n[日立修理ご利用規約 検索] [QRコード]\n\n---\n\n## 【ご相談窓口におけるお客様の個人情報お取り扱いについて】\n- 個人情報は当社の個人情報保護方針に則り適切に管理いたします。  \n- 当社の個人情報保護方針につきましては、[https://corp.hitachi-gls.co.jp/utility/privacy](https://corp.hitachi-gls.co.jp/utility/privacy)をご覧ください。  \n  ※URLは変更する場合があります。日立の家電品ホームページにてご確認ください。  \n- 製品のサービスの提供、各種お問い合わせへの対応に利用させていただきます。また、アンケートをもとにした製品やサービスを向上させるための分析に利用させていただく場合があります。\n\n---\n\n## J-Moss グリーンマークについて\nこのJ-Moss グリーンマークは、特定の化学物質（鉛・水銀・カドミウム・六価クロム・PBB（ポリブロモビフェニル）・PBDE（ポリブロモジフェニルエーテル））の含有率がJIS C 0950:2021 による基準値以下であることを示しています（規定の除外項目を除く）。\n\n詳しい情報は、当社のホームページでご覧いただけます。  \n[https://corp.hitachi-gls.co.jp/_ct/17577871](https://corp.hitachi-gls.co.jp/_ct/17577871)\n\n---\n\n# 愛情点検\n長年ご使用の冷蔵庫の点検を！\n\n**こんな症状はありませんか？**  \n- 電源コード、プラグが異常に熱い。  \n- 電源コードに深い傷や変形がある。  \n- 異臭（焦げ臭いにおい）がする。  \n- 冷蔵庫床面にいつも水がたまっている。  \n- 「ピリピリ」と電気を感じる。  \n- その他の異常や故障がある。\n\n→ **ご使用中止**\n\n故障や事故防止のため、コンセントから電源プラグをはずして、必ず販売店に点検・修理をご相談ください。費用など詳細については販売店にご相談ください。\n\n---\n\n# 廃棄時にご注意願います\n家電リサイクル法では、お客様がご使用済みの冷蔵庫または冷凍庫を廃棄される場合は、収集・運搬料金、再商品化等料金（リサイクル料金）をお支払いいただき、対象品を販売店や市町村に適正に引き渡すことが求められています。\n\n---\n\n35\n```\n",
    "metadata": {
      "topics": [
        "別売部品の案内",
        "お客様相談窓口の連絡方法",
        "修理と部品購入の案内",
        "個人情報の取り扱い",
        "安全点検と廃棄方法"
      ],
      "keywords": [
        "自動製氷用浄水フィルター",
        "冷蔵庫用地震軽倒防止ベルト",
        "調整板",
        "日立家電サポート",
        "修理受付",
        "個人情報保護方針",
        "J-Moss グリーンマーク",
        "家電リサイクル法",
        "問い合わせ電話番号",
        "QRコード"
      ],
      "section_header": "お客様ご相談窓口",
      "page_type": "other"
    }
  },
  {
    "page": 36,
    "summary": "このページは日立冷凍冷蔵庫の保証とアフターサービスについて説明しています。修理依頼の際の連絡内容や保証期間の規定、修理料金の内訳、無料修理の条件および補修用部品の保有期間などが詳述されています。また、保証書の記入や保管の重要性と問い合わせ先の情報も記載されています。",
    "content": "```markdown\n# 保証とアフターサービス\n\n## 修理を依頼されるときは（出張修理）\n\n「お困りのときは」→(P.28〜33)にしたがって調べていただき、なお異常があるときは、必ず電源プラグを抜いてから、お買い上げの販売店にご連絡ください。\n\n### ご連絡していただきたい内容\nアフターサービスをお申しつけいただくときは、下のことをお知らせください。\n\n1. 型式：冷蔵室ドア内側の銘板（シール）に記載されています。  \n2. 故障の状況：できるだけ詳しく。\n\n### 保証期間中は\n修理に際しましては保証書をご提示ください。保証書の規定に従って、販売店が修理させていただきます。なお、保証期間中でも有料になることがありますので、保証書をよくお読みください。\n\n### 保証期間が過ぎているときは\n修理して使用できる場合には、ご希望により有料で修理させていただきます。\n\n---\n\n### 修理料金のしくみ\n修理料金＝技術料＋部品代＋出張料　などで構成されています。\n\n| 名称     | 内容                                                                                                                             |\n|----------|----------------------------------------------------------------------------------------------------------------------------------|\n| 技術料   | 診断、部品交換、調整、修理完了時の点検などの作業にかかる費用です。手数料、人件費、技術教育費、測定機器などの設備費、一般管理費などが含まれます。       |\n| 部品代   | 修理に使用した部品代金です。その他修理に付帯する部材などを含む場合もあります。                                                     |\n| 出張料   | 製品のある場所へ技術者を派遣する場合の費用です。別途、駐車料金をいただく場合があります。                                         |\n\n### 補修用性能部品の保有期間\n冷蔵庫の補修用性能部品の保有期間は、製造打ち切り後9年です。  \n補修用性能部品とは、その製品の機能を維持するために必要な部品です。\n\n---\n\n## 日立冷凍冷蔵庫保証書　 出張修理\n\n| 項目             | 内容                             |\n|------------------|--------------------------------|\n| ※型式           |                                |\n| ※お買い上げ日   | 年　　月　　日                 |\n| 保証期間（お買い上げ日から） | 本体：1年間<br>冷凍サイクル：5年間 |\n| ※お客様         | ご芳名　様<br>ご住所〒<br>電話（   ）  |\n| ※販売店         | 住所・店名<br>電話（   ）       |\n\n※印欄に記入のない場合は無効となりますので必ず「お買い上げ日・販売店名」等の記入をお確かめのうえ、販売店から受け取っていただき内容をよくお読みのあと、大切に保管してください。\n\n---\n\n### ● 冷凍サイクルとは\nコンプレッサー、凝縮器、毛細管、冷却器および配管で構成された冷媒循環回路のことです。なお、冷却器用ファン、冷却器用ファンモーターも含みます。\n\n---\n\n### 《無料修理規定》\n\n1. 取扱説明書、本体貼付けラベル等の注意書きに従った正常な使用状態で保証期間内に故障した場合には、無料修理をさせていただきます。  \n(イ) 保証期間内に故障して無料修理をご依頼になる場合には、お買い上げの販売店にお申し付けください。\n\n2. (ロ) お買い上げの販売店に無料修理をご依頼にならない場合には、「お客様ご相談窓口」→(P.35)の修理のご依頼や修理に関するご相談窓口にご連絡ください。\n\n3. (ハ) この商品は出張修理をさせていただきますので、修理に際し本書を必ずご提示ください。\n\n4. ご転居の場合には事前にお買い上げの販売店にご相談ください。\n\n5. ご贈答品などで本保証書に記入してあるお買い上げの販売店に修理がご依頼になれない場合には、「お客様ご相談窓口」→(P.35)の修理のご依頼や修理に関するご相談窓口にご相談ください。\n\n6. 離島または離島に準ずる遠隔地への出張修理を行なった場合には、出張に要する実費を申し受けます。\n\n7. 保証期間内でも次の場合には原則として有料にさせていただきます。  \n(イ) 使用上の誤り、または改造や不当な修理による故障及び損傷。  \n(ロ) お買い上げ後の取付場所の移動、落下、輸送等による故障及び損傷。  \n(ハ) 火災、地震、風水害、落雷、その他天災地変、塩害、公害、ガス害（硫化ガスなど）や異常電圧、指定外の使用電源（電圧、周波数）による故障及び損傷。  \n(ニ) 一般家庭用以外（例えば業務用等への長時間使用及び車両、船舶への搭載に使用される場合）の故障及び損傷。  \n(ホ) 故障の原因が本機以外にある場合で改善を要するとき。  \n(ヘ) 本書のご提示がない場合。  \n(ト) 本書にお買い上げ年月日、お客様名、販売店名の記入がない場合、あるいは字句を書き換えられた場合。\n\n8. 食品の補償等、商品修理以外の責はご容赦ください。\n\n9. 修理の際、弊社の品質基準に適合した再利用部品を使用することがあります。\n\n10. 本書は再発行しませんので紛失しないよう大切に保管してください。\n\n11. 本書は日本国内においてのみ有効です。  \nThis warranty is valid only in Japan.\n\n---\n\n●お客様にご記入いただいた保証書の写しの個人情報は、保証期間内のサービス活動及びその後の安全点検活動のために記載内容を利用させていただく場合がございますので、ご了解ください。  \n●この保証書は本書に明示した期間、条件のもとにおいて無償修理をお約束するものです。したがってこの保証書によって保証書を発行している者（保証責任者）、及びそれ以外の事業者に対するお客様の法律上の権利を制限するものではありませんので、保証期間経過後の修理等についてご不明の場合は、お買い上げの販売店または「お客様ご相談窓口」→(P.35)の修理のご依頼や修理に関するご相談窓口にお問い合わせください。\n\n---\n\n日立グローバルライフソリューションズ株式会社  \n〒105-8410 東京都港区西新橋 2-15-12  \nお問合せ先：「修理に関するご相談窓口」0120-3121-68、携帯 0570-0031-68  \n詳しくは「お客様ご相談窓口」のページをご覧ください。\n```\n",
    "metadata": {
      "topics": [
        "修理依頼方法",
        "保証期間と修理対応",
        "修理料金の仕組み",
        "無料修理規定",
        "補修用性能部品の保有期間"
      ],
      "keywords": [
        "日立冷凍冷蔵庫",
        "保証書",
        "出張修理",
        "修理料金",
        "補修用性能部品",
        "冷凍サイクル",
        "無料修理",
        "販売店",
        "アフターサービス",
        "技術料"
      ],
      "section_header": "保証とアフターサービス",
      "page_type": "maintenance"
    }
  }
]